[[{"id":"H66","haps":["EPI_ISL_414430"]},{"id":"I272"},{"haps":["EPI_ISL_407988","EPI_ISL_408481","EPI_ISL_412030","EPI_ISL_412968","EPI_ISL_413870","EPI_ISL_413896","EPI_ISL_414483","EPI_ISL_414484","EPI_ISL_414485","EPI_ISL_414501","EPI_ISL_414571","EPI_ISL_415137","EPI_ISL_415577","EPI_ISL_415578","EPI_ISL_415579","EPI_ISL_415580","EPI_ISL_415585","EPI_ISL_415587","EPI_ISL_416342","EPI_ISL_416351","EPI_ISL_416354","EPI_ISL_416383","EPI_ISL_416414","EPI_ISL_416526","EPI_ISL_416566","EPI_ISL_416568","EPI_ISL_416569","EPI_ISL_416571","EPI_ISL_416572","EPI_ISL_416573","EPI_ISL_416574","EPI_ISL_416575","EPI_ISL_416576","EPI_ISL_416577","EPI_ISL_416578","EPI_ISL_416579","EPI_ISL_416580","EPI_ISL_416581","EPI_ISL_416583","EPI_ISL_416586","EPI_ISL_416588","EPI_ISL_416589","EPI_ISL_416590","EPI_ISL_416591","EPI_ISL_416592","EPI_ISL_416593","EPI_ISL_416594","EPI_ISL_416595","EPI_ISL_416596","EPI_ISL_416597","EPI_ISL_416600","EPI_ISL_416601","EPI_ISL_416602","EPI_ISL_416605","EPI_ISL_416606","EPI_ISL_416607","EPI_ISL_416608","EPI_ISL_416609","EPI_ISL_416611","EPI_ISL_416612","EPI_ISL_416614","EPI_ISL_416616","EPI_ISL_416617","EPI_ISL_416618","EPI_ISL_416620","EPI_ISL_416621","EPI_ISL_416622","EPI_ISL_416623","EPI_ISL_416626","EPI_ISL_416627","EPI_ISL_416628","EPI_ISL_416629","EPI_ISL_416630","EPI_ISL_416631","EPI_ISL_416632","EPI_ISL_416633","EPI_ISL_416634","EPI_ISL_417920"],"id":"H18"},{"haps":["EPI_ISL_416432","EPI_ISL_416449","EPI_ISL_416706","EPI_ISL_417033","EPI_ISL_417388","EPI_ISL_417396","EPI_ISL_417400","EPI_ISL_417401","EPI_ISL_417403","EPI_ISL_417917","EPI_ISL_417918"],"id":"H129"},{"haps":["EPI_ISL_410546","EPI_ISL_412974","EPI_ISL_413605","EPI_ISL_414529","EPI_ISL_414531","EPI_ISL_414532","EPI_ISL_414534","EPI_ISL_414645","EPI_ISL_415130","EPI_ISL_415132","EPI_ISL_415139","EPI_ISL_415143","EPI_ISL_415144","EPI_ISL_415149","EPI_ISL_415470","EPI_ISL_415484","EPI_ISL_415590","EPI_ISL_415641","EPI_ISL_415643","EPI_ISL_415709","EPI_ISL_416480","EPI_ISL_416503","EPI_ISL_416507","EPI_ISL_416515","EPI_ISL_416516","EPI_ISL_416518","EPI_ISL_417011","EPI_ISL_417215","EPI_ISL_417216","EPI_ISL_417219","EPI_ISL_417254","EPI_ISL_417262","EPI_ISL_417275","EPI_ISL_417281","EPI_ISL_417284","EPI_ISL_417300","EPI_ISL_417303","EPI_ISL_417305","EPI_ISL_417314","EPI_ISL_417486","EPI_ISL_417487","EPI_ISL_417488","EPI_ISL_417489","EPI_ISL_417490","EPI_ISL_417554","EPI_ISL_417601","EPI_ISL_417605","EPI_ISL_417657","EPI_ISL_417658","EPI_ISL_417661","EPI_ISL_417668","EPI_ISL_417669","EPI_ISL_417765","EPI_ISL_417952","EPI_ISL_418025","EPI_ISL_418126"],"id":"H24"},{"haps":["EPI_ISL_413025","EPI_ISL_413603","EPI_ISL_414009","EPI_ISL_417212","EPI_ISL_417483","EPI_ISL_418080"],"id":"H41"},{"haps":["EPI_ISL_417267","EPI_ISL_417268","EPI_ISL_417269","EPI_ISL_417399"],"id":"H162"},{"id":"H28","haps":["EPI_ISL_412116","EPI_ISL_414005","EPI_ISL_414006","EPI_ISL_414007","EPI_ISL_415128","EPI_ISL_415478","EPI_ISL_415630","EPI_ISL_417213","EPI_ISL_417270","EPI_ISL_417282","EPI_ISL_417315","EPI_ISL_417394","EPI_ISL_417409","EPI_ISL_417410","EPI_ISL_417475","EPI_ISL_417498","EPI_ISL_417584","EPI_ISL_417659","EPI_ISL_417950","EPI_ISL_418020","EPI_ISL_418021"]},{"haps":["EPI_ISL_418243"],"id":"H210"},{"id":"H36","haps":["EPI_ISL_413016","EPI_ISL_413019","EPI_ISL_414011","EPI_ISL_414013","EPI_ISL_414451","EPI_ISL_414468","EPI_ISL_415142","EPI_ISL_415486","EPI_ISL_415491","EPI_ISL_415512","EPI_ISL_415527","EPI_ISL_417008","EPI_ISL_417009","EPI_ISL_417189","EPI_ISL_417246","EPI_ISL_417290","EPI_ISL_417291","EPI_ISL_417346","EPI_ISL_417405","EPI_ISL_417522","EPI_ISL_417528","EPI_ISL_417825","EPI_ISL_417931","EPI_ISL_417975","EPI_ISL_418005","EPI_ISL_418149"]},{"haps":["EPI_ISL_415631","EPI_ISL_417478","EPI_ISL_417501"],"id":"H111"},{"id":"H148","haps":["EPI_ISL_416646","EPI_ISL_416675","EPI_ISL_416723","EPI_ISL_416733","EPI_ISL_417280","EPI_ISL_417289","EPI_ISL_417408","EPI_ISL_417574","EPI_ISL_417670","EPI_ISL_417732"]},{"haps":["EPI_ISL_417017"],"id":"H154"},{"haps":["EPI_ISL_417025"],"id":"H157"},{"id":"H183","haps":["EPI_ISL_417580","EPI_ISL_417590","EPI_ISL_417611","EPI_ISL_417621","EPI_ISL_417655","EPI_ISL_417660","EPI_ISL_417699","EPI_ISL_417822"]},{"haps":["EPI_ISL_416032","EPI_ISL_417672"],"id":"H118"},{"haps":["EPI_ISL_417540","EPI_ISL_417541","EPI_ISL_417545","EPI_ISL_417603","EPI_ISL_417801"],"id":"H177"},{"haps":["EPI_ISL_415492"],"id":"H103"},{"haps":["EPI_ISL_417544","EPI_ISL_417548","EPI_ISL_417557","EPI_ISL_417558","EPI_ISL_417568","EPI_ISL_417606","EPI_ISL_417607","EPI_ISL_417653","EPI_ISL_417696","EPI_ISL_417716","EPI_ISL_417750","EPI_ISL_417771","EPI_ISL_417772","EPI_ISL_417838","EPI_ISL_417864"],"id":"H178"},{"haps":["EPI_ISL_418060"],"id":"H206"},{"id":"H163","haps":["EPI_ISL_417292"]},{"haps":["EPI_ISL_415540"],"id":"H106"},{"id":"H105","haps":["EPI_ISL_415539"]},{"id":"H143","haps":["EPI_ISL_416567","EPI_ISL_416584","EPI_ISL_416599"]},{"haps":["EPI_ISL_408430","EPI_ISL_410984","EPI_ISL_411218"],"id":"H19"},{"haps":["EPI_ISL_416615"],"id":"H146"},{"haps":["EPI_ISL_416585"],"id":"H144"},{"haps":["EPI_ISL_413607"],"id":"H54"},{"haps":["EPI_ISL_402119","EPI_ISL_402120","EPI_ISL_402121","EPI_ISL_402123","EPI_ISL_402124","EPI_ISL_402125","EPI_ISL_402127","EPI_ISL_402128","EPI_ISL_402129","EPI_ISL_402130","EPI_ISL_402132","EPI_ISL_403928","EPI_ISL_403929","EPI_ISL_403930","EPI_ISL_403931","EPI_ISL_403934","EPI_ISL_403962","EPI_ISL_403963","EPI_ISL_404227","EPI_ISL_404228","EPI_ISL_404253","EPI_ISL_406538","EPI_ISL_406595","EPI_ISL_406716","EPI_ISL_406717","EPI_ISL_406798","EPI_ISL_406800","EPI_ISL_406970","EPI_ISL_406973","EPI_ISL_407079","EPI_ISL_407084","EPI_ISL_407313","EPI_ISL_408431","EPI_ISL_408479","EPI_ISL_408486","EPI_ISL_408488","EPI_ISL_408511","EPI_ISL_408514","EPI_ISL_408515","EPI_ISL_408976","EPI_ISL_410044","EPI_ISL_410218","EPI_ISL_410486","EPI_ISL_410531","EPI_ISL_410532","EPI_ISL_411902","EPI_ISL_411915","EPI_ISL_411927","EPI_ISL_411950","EPI_ISL_411953","EPI_ISL_411955","EPI_ISL_412026","EPI_ISL_412459","EPI_ISL_412872","EPI_ISL_412898","EPI_ISL_412899","EPI_ISL_412900","EPI_ISL_412965","EPI_ISL_413564","EPI_ISL_413567","EPI_ISL_413568","EPI_ISL_413576","EPI_ISL_413578","EPI_ISL_413580","EPI_ISL_413581","EPI_ISL_413582","EPI_ISL_413585","EPI_ISL_413586","EPI_ISL_413590","EPI_ISL_413594","EPI_ISL_413596","EPI_ISL_413606","EPI_ISL_413608","EPI_ISL_413610","EPI_ISL_413613","EPI_ISL_413614","EPI_ISL_413615","EPI_ISL_413616","EPI_ISL_413618","EPI_ISL_413619","EPI_ISL_413620","EPI_ISL_413621","EPI_ISL_413622","EPI_ISL_413623","EPI_ISL_413692","EPI_ISL_413693","EPI_ISL_413694","EPI_ISL_413753","EPI_ISL_413850","EPI_ISL_413851","EPI_ISL_413852","EPI_ISL_413857","EPI_ISL_413861","EPI_ISL_413866","EPI_ISL_413868","EPI_ISL_413869","EPI_ISL_413872","EPI_ISL_413874","EPI_ISL_413875","EPI_ISL_413879","EPI_ISL_413882","EPI_ISL_413883","EPI_ISL_413884","EPI_ISL_413888","EPI_ISL_413893","EPI_ISL_413898","EPI_ISL_413902","EPI_ISL_414024","EPI_ISL_414026","EPI_ISL_414040","EPI_ISL_414041","EPI_ISL_414042","EPI_ISL_414043","EPI_ISL_414044","EPI_ISL_414426","EPI_ISL_414427","EPI_ISL_414431","EPI_ISL_414432","EPI_ISL_414458","EPI_ISL_414459","EPI_ISL_414462","EPI_ISL_414467","EPI_ISL_414479","EPI_ISL_414481","EPI_ISL_414487","EPI_ISL_414498","EPI_ISL_414504","EPI_ISL_414506","EPI_ISL_414508","EPI_ISL_414510","EPI_ISL_414533","EPI_ISL_414538","EPI_ISL_414540","EPI_ISL_414541","EPI_ISL_414542","EPI_ISL_414547","EPI_ISL_414550","EPI_ISL_414553","EPI_ISL_414574","EPI_ISL_414687","EPI_ISL_414692","EPI_ISL_415148","EPI_ISL_415490","EPI_ISL_415493","EPI_ISL_415494","EPI_ISL_415504","EPI_ISL_415513","EPI_ISL_415516","EPI_ISL_415522","EPI_ISL_415528","EPI_ISL_415538","EPI_ISL_415583","EPI_ISL_415628","EPI_ISL_415638","EPI_ISL_415659","EPI_ISL_415711","EPI_ISL_415918","EPI_ISL_415919","EPI_ISL_416044","EPI_ISL_416046","EPI_ISL_416047","EPI_ISL_416320","EPI_ISL_416329","EPI_ISL_416336","EPI_ISL_416337","EPI_ISL_416340","EPI_ISL_416345","EPI_ISL_416347","EPI_ISL_416348","EPI_ISL_416353","EPI_ISL_416355","EPI_ISL_416358","EPI_ISL_416359","EPI_ISL_416360","EPI_ISL_416362","EPI_ISL_416367","EPI_ISL_416369","EPI_ISL_416370","EPI_ISL_416371","EPI_ISL_416374","EPI_ISL_416375","EPI_ISL_416376","EPI_ISL_416379","EPI_ISL_416380","EPI_ISL_416384","EPI_ISL_416385","EPI_ISL_416388","EPI_ISL_416390","EPI_ISL_416393","EPI_ISL_416394","EPI_ISL_416395","EPI_ISL_416396","EPI_ISL_416401","EPI_ISL_416404","EPI_ISL_416405","EPI_ISL_416416","EPI_ISL_416425","EPI_ISL_416474","EPI_ISL_416738","EPI_ISL_416907","EPI_ISL_417064","EPI_ISL_417178","EPI_ISL_417218","EPI_ISL_417253","EPI_ISL_417259","EPI_ISL_417263","EPI_ISL_417276","EPI_ISL_417285","EPI_ISL_417288","EPI_ISL_417296","EPI_ISL_417306","EPI_ISL_417312","EPI_ISL_417313","EPI_ISL_417318","EPI_ISL_417320","EPI_ISL_417325","EPI_ISL_417335","EPI_ISL_417432","EPI_ISL_417482","EPI_ISL_417553","EPI_ISL_417576","EPI_ISL_417591","EPI_ISL_417602","EPI_ISL_417616","EPI_ISL_417792","EPI_ISL_418083","EPI_ISL_418084","EPI_ISL_418085","EPI_ISL_418092","EPI_ISL_418100","EPI_ISL_418101","EPI_ISL_418102","EPI_ISL_418103","EPI_ISL_418104","EPI_ISL_418106","EPI_ISL_418107","EPI_ISL_418108","EPI_ISL_418111","EPI_ISL_418112","EPI_ISL_418115","EPI_ISL_418120","EPI_ISL_418121","EPI_ISL_418124","EPI_ISL_418125","EPI_ISL_418127","EPI_ISL_418128","EPI_ISL_418129","EPI_ISL_418130","EPI_ISL_418131","EPI_ISL_418132","EPI_ISL_418133","EPI_ISL_418134","EPI_ISL_418135","EPI_ISL_418137","EPI_ISL_418140","EPI_ISL_418141","EPI_ISL_418142","EPI_ISL_418143","EPI_ISL_418148","EPI_ISL_418150","EPI_ISL_418153","EPI_ISL_418154","EPI_ISL_418157","EPI_ISL_418160","EPI_ISL_418161","EPI_ISL_418162","EPI_ISL_418164","EPI_ISL_418165"],"id":"H1"},{"haps":["EPI_ISL_413573","EPI_ISL_413577","EPI_ISL_413583","EPI_ISL_414452","EPI_ISL_414500","EPI_ISL_414543","EPI_ISL_414551","EPI_ISL_415479","EPI_ISL_415489","EPI_ISL_415505","EPI_ISL_415507","EPI_ISL_415510","EPI_ISL_415517","EPI_ISL_415519","EPI_ISL_416740","EPI_ISL_417211","EPI_ISL_417264","EPI_ISL_417283","EPI_ISL_418026"],"id":"H48"},{"haps":["EPI_ISL_414589","EPI_ISL_415500","EPI_ISL_415501","EPI_ISL_415506","EPI_ISL_415508","EPI_ISL_415509","EPI_ISL_415524","EPI_ISL_417460","EPI_ISL_417880"],"id":"H82"},{"haps":["EPI_ISL_414536","EPI_ISL_414544","EPI_ISL_415521"],"id":"H72"},{"haps":["EPI_ISL_416397"],"id":"H124"},{"haps":["EPI_ISL_413611","EPI_ISL_413612"],"id":"H56"},{"id":"H10","haps":["EPI_ISL_406535","EPI_ISL_406536","EPI_ISL_408670","EPI_ISL_410719","EPI_ISL_411066","EPI_ISL_412967","EPI_ISL_413522","EPI_ISL_416324","EPI_ISL_416398"]},{"id":"I85"},{"haps":["EPI_ISL_415657","EPI_ISL_415920","EPI_ISL_418110","EPI_ISL_418136","EPI_ISL_418144","EPI_ISL_418145","EPI_ISL_418147","EPI_ISL_418151","EPI_ISL_418155","EPI_ISL_418156","EPI_ISL_418158","EPI_ISL_418159","EPI_ISL_418163"],"id":"H113"},{"id":"H45","haps":["EPI_ISL_413488","EPI_ISL_414497","EPI_ISL_414499","EPI_ISL_414505","EPI_ISL_414509","EPI_ISL_415464","EPI_ISL_415495","EPI_ISL_415531","EPI_ISL_416033","EPI_ISL_416488","EPI_ISL_417412","EPI_ISL_417459","EPI_ISL_417461","EPI_ISL_417462","EPI_ISL_417759","EPI_ISL_417793","EPI_ISL_417958","EPI_ISL_418117"]},{"haps":["EPI_ISL_406031","EPI_ISL_406036","EPI_ISL_406844","EPI_ISL_408977","EPI_ISL_408978","EPI_ISL_410536","EPI_ISL_410545","EPI_ISL_410713","EPI_ISL_410714","EPI_ISL_410715","EPI_ISL_410716","EPI_ISL_411929","EPI_ISL_411951","EPI_ISL_413018","EPI_ISL_413863","EPI_ISL_415582","EPI_ISL_416315","EPI_ISL_416325","EPI_ISL_416346","EPI_ISL_416349","EPI_ISL_416364","EPI_ISL_416391","EPI_ISL_416400","EPI_ISL_416408","EPI_ISL_416410","EPI_ISL_416411","EPI_ISL_417177","EPI_ISL_417179","EPI_ISL_417180","EPI_ISL_417182","EPI_ISL_417183","EPI_ISL_417184","EPI_ISL_417185","EPI_ISL_417190","EPI_ISL_417195","EPI_ISL_417199","EPI_ISL_418123"],"id":"H5"},{"id":"H27","haps":["EPI_ISL_412029","EPI_ISL_414527","EPI_ISL_414528","EPI_ISL_414569","EPI_ISL_416314","EPI_ISL_417181","EPI_ISL_417187","EPI_ISL_417188","EPI_ISL_417193","EPI_ISL_417197"]},{"haps":["EPI_ISL_414517","EPI_ISL_414519"],"id":"H69"},{"haps":["EPI_ISL_406596","EPI_ISL_406597","EPI_ISL_410720","EPI_ISL_411219","EPI_ISL_411220"],"id":"H12"},{"haps":["EPI_ISL_403936","EPI_ISL_403937","EPI_ISL_406531","EPI_ISL_408010","EPI_ISL_411952","EPI_ISL_416321"],"id":"H3"},{"haps":["EPI_ISL_406801","EPI_ISL_407071","EPI_ISL_407073","EPI_ISL_407893","EPI_ISL_407976","EPI_ISL_408483","EPI_ISL_408489","EPI_ISL_411926","EPI_ISL_412869","EPI_ISL_412978","EPI_ISL_412979","EPI_ISL_412980","EPI_ISL_412983","EPI_ISL_413485","EPI_ISL_413523","EPI_ISL_413691","EPI_ISL_413695","EPI_ISL_413729","EPI_ISL_413746","EPI_ISL_413747","EPI_ISL_413748","EPI_ISL_413749","EPI_ISL_413750","EPI_ISL_413751","EPI_ISL_413752","EPI_ISL_413854","EPI_ISL_413856","EPI_ISL_413858","EPI_ISL_413859","EPI_ISL_413860","EPI_ISL_413867","EPI_ISL_413873","EPI_ISL_413889","EPI_ISL_413897","EPI_ISL_414378","EPI_ISL_414379","EPI_ISL_414380","EPI_ISL_414496","EPI_ISL_414577","EPI_ISL_414578","EPI_ISL_414689","EPI_ISL_414690","EPI_ISL_414691","EPI_ISL_414934","EPI_ISL_416042","EPI_ISL_416322","EPI_ISL_416323","EPI_ISL_416326","EPI_ISL_416328","EPI_ISL_416330","EPI_ISL_416333","EPI_ISL_416339","EPI_ISL_416343","EPI_ISL_416344","EPI_ISL_416352","EPI_ISL_416357","EPI_ISL_416368","EPI_ISL_416378","EPI_ISL_416402","EPI_ISL_416483","EPI_ISL_416485","EPI_ISL_416885","EPI_ISL_417176","EPI_ISL_417205","EPI_ISL_417206","EPI_ISL_417518","EPI_ISL_417924","EPI_ISL_417979","EPI_ISL_417980","EPI_ISL_418027","EPI_ISL_418146","EPI_ISL_418252"],"id":"H13"},{"haps":["EPI_ISL_412982"],"id":"H35"},{"haps":["EPI_ISL_413711"],"id":"H60"},{"haps":["EPI_ISL_404895","EPI_ISL_407214","EPI_ISL_407215","EPI_ISL_408478","EPI_ISL_408487","EPI_ISL_411060","EPI_ISL_413855","EPI_ISL_413862","EPI_ISL_416473","EPI_ISL_416886"],"id":"H4"},{"id":"I65"},{"haps":["EPI_ISL_413455","EPI_ISL_413456","EPI_ISL_413457","EPI_ISL_413458","EPI_ISL_413557","EPI_ISL_413560","EPI_ISL_413562","EPI_ISL_413563","EPI_ISL_413601","EPI_ISL_413649","EPI_ISL_413652","EPI_ISL_413653","EPI_ISL_413922","EPI_ISL_413924","EPI_ISL_414363","EPI_ISL_414364","EPI_ISL_414365","EPI_ISL_414366","EPI_ISL_414367","EPI_ISL_414368","EPI_ISL_414369","EPI_ISL_414590","EPI_ISL_414592","EPI_ISL_414593","EPI_ISL_414596","EPI_ISL_414597","EPI_ISL_414619","EPI_ISL_414620","EPI_ISL_414621","EPI_ISL_415541","EPI_ISL_415542","EPI_ISL_415586","EPI_ISL_415589","EPI_ISL_415591","EPI_ISL_415592","EPI_ISL_415593","EPI_ISL_415594","EPI_ISL_415595","EPI_ISL_415598","EPI_ISL_415599","EPI_ISL_415603","EPI_ISL_415604","EPI_ISL_415606","EPI_ISL_415610","EPI_ISL_415612","EPI_ISL_415613","EPI_ISL_415614","EPI_ISL_415615","EPI_ISL_415616","EPI_ISL_415617","EPI_ISL_415618","EPI_ISL_415619","EPI_ISL_415621","EPI_ISL_415622","EPI_ISL_415623","EPI_ISL_415626","EPI_ISL_415627","EPI_ISL_416417","EPI_ISL_416423","EPI_ISL_416424","EPI_ISL_416433","EPI_ISL_416436","EPI_ISL_416437","EPI_ISL_416441","EPI_ISL_416442","EPI_ISL_416443","EPI_ISL_416444","EPI_ISL_416445","EPI_ISL_416446","EPI_ISL_416448","EPI_ISL_416450","EPI_ISL_416451","EPI_ISL_416454","EPI_ISL_416455","EPI_ISL_416456","EPI_ISL_416460","EPI_ISL_416461","EPI_ISL_416465","EPI_ISL_416514","EPI_ISL_416636","EPI_ISL_416637","EPI_ISL_416638","EPI_ISL_416639","EPI_ISL_416640","EPI_ISL_416641","EPI_ISL_416643","EPI_ISL_416644","EPI_ISL_416645","EPI_ISL_416652","EPI_ISL_416654","EPI_ISL_416656","EPI_ISL_416659","EPI_ISL_416662","EPI_ISL_416663","EPI_ISL_416665","EPI_ISL_416666","EPI_ISL_416669","EPI_ISL_416670","EPI_ISL_416679","EPI_ISL_416680","EPI_ISL_416681","EPI_ISL_416683","EPI_ISL_416685","EPI_ISL_416686","EPI_ISL_416687","EPI_ISL_416688","EPI_ISL_416689","EPI_ISL_416690","EPI_ISL_416692","EPI_ISL_416695","EPI_ISL_416701","EPI_ISL_416702","EPI_ISL_416703","EPI_ISL_416705","EPI_ISL_416709","EPI_ISL_416710","EPI_ISL_416711","EPI_ISL_416712","EPI_ISL_416714","EPI_ISL_416715","EPI_ISL_416717","EPI_ISL_416718","EPI_ISL_416720","EPI_ISL_416721","EPI_ISL_416722","EPI_ISL_416726","EPI_ISL_416727","EPI_ISL_417028","EPI_ISL_417065","EPI_ISL_417066","EPI_ISL_417067","EPI_ISL_417068","EPI_ISL_417069","EPI_ISL_417070","EPI_ISL_417071","EPI_ISL_417074","EPI_ISL_417077","EPI_ISL_417078","EPI_ISL_417079","EPI_ISL_417080","EPI_ISL_417082","EPI_ISL_417083","EPI_ISL_417084","EPI_ISL_417086","EPI_ISL_417087","EPI_ISL_417088","EPI_ISL_417089","EPI_ISL_417090","EPI_ISL_417091","EPI_ISL_417092","EPI_ISL_417093","EPI_ISL_417094","EPI_ISL_417096","EPI_ISL_417097","EPI_ISL_417098","EPI_ISL_417099","EPI_ISL_417102","EPI_ISL_417103","EPI_ISL_417104","EPI_ISL_417105","EPI_ISL_417106","EPI_ISL_417107","EPI_ISL_417108","EPI_ISL_417109","EPI_ISL_417110","EPI_ISL_417112","EPI_ISL_417113","EPI_ISL_417114","EPI_ISL_417115","EPI_ISL_417116","EPI_ISL_417117","EPI_ISL_417118","EPI_ISL_417119","EPI_ISL_417120","EPI_ISL_417121","EPI_ISL_417122","EPI_ISL_417123","EPI_ISL_417124","EPI_ISL_417125","EPI_ISL_417127","EPI_ISL_417128","EPI_ISL_417129","EPI_ISL_417130","EPI_ISL_417131","EPI_ISL_417132","EPI_ISL_417133","EPI_ISL_417134","EPI_ISL_417135","EPI_ISL_417136","EPI_ISL_417137","EPI_ISL_417138","EPI_ISL_417140","EPI_ISL_417141","EPI_ISL_417142","EPI_ISL_417143","EPI_ISL_417144","EPI_ISL_417145","EPI_ISL_417146","EPI_ISL_417148","EPI_ISL_417149","EPI_ISL_417150","EPI_ISL_417151","EPI_ISL_417152","EPI_ISL_417153","EPI_ISL_417154","EPI_ISL_417155","EPI_ISL_417156","EPI_ISL_417157","EPI_ISL_417158","EPI_ISL_417161","EPI_ISL_417162","EPI_ISL_417164","EPI_ISL_417165","EPI_ISL_417166","EPI_ISL_417167","EPI_ISL_417168","EPI_ISL_417169","EPI_ISL_417170","EPI_ISL_417171","EPI_ISL_417172","EPI_ISL_417173","EPI_ISL_417174","EPI_ISL_417175","EPI_ISL_417203","EPI_ISL_417323","EPI_ISL_417324","EPI_ISL_417332","EPI_ISL_417344","EPI_ISL_417349","EPI_ISL_417350","EPI_ISL_417351","EPI_ISL_417354","EPI_ISL_417355","EPI_ISL_417357","EPI_ISL_417358","EPI_ISL_417360","EPI_ISL_417361","EPI_ISL_417364","EPI_ISL_417365","EPI_ISL_417366","EPI_ISL_417368","EPI_ISL_417371","EPI_ISL_417375","EPI_ISL_417377","EPI_ISL_417449","EPI_ISL_417450","EPI_ISL_417456","EPI_ISL_417507","EPI_ISL_417960","EPI_ISL_417962","EPI_ISL_417964","EPI_ISL_417965","EPI_ISL_417966","EPI_ISL_417968","EPI_ISL_418030","EPI_ISL_418034","EPI_ISL_418038","EPI_ISL_418040","EPI_ISL_418046","EPI_ISL_418047","EPI_ISL_418048","EPI_ISL_418050","EPI_ISL_418059","EPI_ISL_418061","EPI_ISL_418063","EPI_ISL_418064","EPI_ISL_418065","EPI_ISL_418066","EPI_ISL_418069","EPI_ISL_418070","EPI_ISL_418074","EPI_ISL_418075","EPI_ISL_418078","EPI_ISL_418079","EPI_ISL_418082","EPI_ISL_418113","EPI_ISL_418187","EPI_ISL_418189"],"id":"H44"},{"id":"I44"},{"id":"H185","haps":["EPI_ISL_417618","EPI_ISL_417720"]},{"id":"H182","haps":["EPI_ISL_417577","EPI_ISL_417615","EPI_ISL_417717","EPI_ISL_417724","EPI_ISL_417762","EPI_ISL_417789","EPI_ISL_417791","EPI_ISL_417818"]},{"id":"H196","haps":["EPI_ISL_417871"]},{"id":"H127","haps":["EPI_ISL_416413","EPI_ISL_417031","EPI_ISL_417194","EPI_ISL_417395","EPI_ISL_417477","EPI_ISL_417500","EPI_ISL_417504","EPI_ISL_417587","EPI_ISL_418062"]},{"haps":["EPI_ISL_414617"],"id":"H85"},{"id":"H130","haps":["EPI_ISL_416447","EPI_ISL_417081","EPI_ISL_417085","EPI_ISL_418055","EPI_ISL_418077"]},{"id":"H165","haps":["EPI_ISL_417353","EPI_ISL_417380"]},{"haps":["EPI_ISL_417147"],"id":"H159"},{"id":"H168","haps":["EPI_ISL_417369"]},{"haps":["EPI_ISL_415608","EPI_ISL_415609","EPI_ISL_415624","EPI_ISL_416650","EPI_ISL_416651","EPI_ISL_416684","EPI_ISL_417378"],"id":"H109"},{"id":"I57"},{"id":"H107","haps":["EPI_ISL_415584","EPI_ISL_415588"]},{"haps":["EPI_ISL_416657"],"id":"H149"},{"haps":["EPI_ISL_414595","EPI_ISL_414622","EPI_ISL_415602","EPI_ISL_416439","EPI_ISL_416453","EPI_ISL_417448"],"id":"H83"},{"id":"H152","haps":["EPI_ISL_416700"]},{"id":"H151","haps":["EPI_ISL_416664"]},{"id":"H153","haps":["EPI_ISL_416728"]},{"id":"H108","haps":["EPI_ISL_415607","EPI_ISL_416440"]},{"haps":["EPI_ISL_417348"],"id":"H164"},{"haps":["EPI_ISL_413650","EPI_ISL_413651","EPI_ISL_414618","EPI_ISL_415596","EPI_ISL_415605","EPI_ISL_417072","EPI_ISL_417073","EPI_ISL_417075","EPI_ISL_417076","EPI_ISL_417111","EPI_ISL_417139","EPI_ISL_417159","EPI_ISL_417160","EPI_ISL_418029","EPI_ISL_418071"],"id":"H58"},{"haps":["EPI_ISL_413925","EPI_ISL_413926","EPI_ISL_413928","EPI_ISL_413931","EPI_ISL_414588"],"id":"H61"},{"id":"H158","haps":["EPI_ISL_417126"]},{"id":"H167","haps":["EPI_ISL_417367"]},{"id":"H166","haps":["EPI_ISL_417363"]},{"id":"H110","haps":["EPI_ISL_415611","EPI_ISL_415620","EPI_ISL_416635","EPI_ISL_416649","EPI_ISL_416668","EPI_ISL_416682","EPI_ISL_416694","EPI_ISL_416713","EPI_ISL_417356","EPI_ISL_417370","EPI_ISL_417381","EPI_ISL_417453"]},{"haps":["EPI_ISL_412970","EPI_ISL_413486","EPI_ISL_413487","EPI_ISL_415600","EPI_ISL_416435","EPI_ISL_416462","EPI_ISL_417095","EPI_ISL_417100","EPI_ISL_417101","EPI_ISL_417347"],"id":"H34"},{"id":"H131","haps":["EPI_ISL_416466","EPI_ISL_416667","EPI_ISL_416677","EPI_ISL_417163","EPI_ISL_417374","EPI_ISL_417480","EPI_ISL_417503"]},{"id":"H128","haps":["EPI_ISL_416419","EPI_ISL_416421"]},{"haps":["EPI_ISL_407894","EPI_ISL_407896","EPI_ISL_410535","EPI_ISL_410717","EPI_ISL_410718","EPI_ISL_411954","EPI_ISL_413853","EPI_ISL_416316","EPI_ISL_416317","EPI_ISL_416403","EPI_ISL_416415","EPI_ISL_416696"],"id":"H16"},{"haps":["EPI_ISL_415461","EPI_ISL_415526","EPI_ISL_417200","EPI_ISL_417201","EPI_ISL_417514"],"id":"H98"},{"id":"H77","haps":["EPI_ISL_414555"]},{"haps":["EPI_ISL_408480","EPI_ISL_416392"],"id":"H20"},{"haps":["EPI_ISL_412873"],"id":"H30"},{"id":"H7","haps":["EPI_ISL_406223"]},{"haps":["EPI_ISL_403932","EPI_ISL_403933","EPI_ISL_403935","EPI_ISL_405839","EPI_ISL_406030","EPI_ISL_406593","EPI_ISL_408665","EPI_ISL_408666","EPI_ISL_408667","EPI_ISL_411956","EPI_ISL_413809","EPI_ISL_414521","EPI_ISL_414688","EPI_ISL_416318","EPI_ISL_416319","EPI_ISL_416366","EPI_ISL_416377","EPI_ISL_417030"],"id":"H2"},{"haps":["EPI_ISL_406592"],"id":"H11"},{"haps":["EPI_ISL_416372"],"id":"H122"},{"id":"H202","haps":["EPI_ISL_417981"]},{"haps":["EPI_ISL_414579","EPI_ISL_414598","EPI_ISL_414600","EPI_ISL_414623","EPI_ISL_415151","EPI_ISL_415503","EPI_ISL_415658","EPI_ISL_415660","EPI_ISL_415661","EPI_ISL_416477","EPI_ISL_416484","EPI_ISL_416487","EPI_ISL_416994","EPI_ISL_417034","EPI_ISL_417961","EPI_ISL_418216"],"id":"H81"},{"id":"I28"},{"id":"H141","haps":["EPI_ISL_416539"]},{"haps":["EPI_ISL_406034","EPI_ISL_408484","EPI_ISL_408485","EPI_ISL_408668","EPI_ISL_410045","EPI_ISL_416338","EPI_ISL_416341","EPI_ISL_416381","EPI_ISL_416409","EPI_ISL_416427","EPI_ISL_416429"],"id":"H6"},{"haps":["EPI_ISL_412028"],"id":"H26"},{"haps":["EPI_ISL_416538","EPI_ISL_418045"],"id":"H140"},{"haps":["EPI_ISL_407193","EPI_ISL_412870","EPI_ISL_412871","EPI_ISL_413513","EPI_ISL_413514","EPI_ISL_413515","EPI_ISL_413516","EPI_ISL_413518","EPI_ISL_413519","EPI_ISL_413520","EPI_ISL_413521"],"id":"H15"},{"id":"H37","haps":["EPI_ISL_413017"]},{"haps":["EPI_ISL_413697","EPI_ISL_413761","EPI_ISL_413791","EPI_ISL_416335","EPI_ISL_416350"],"id":"H59"},{"id":"H29","haps":["EPI_ISL_412862","EPI_ISL_413558","EPI_ISL_413559","EPI_ISL_413561"]},{"haps":["EPI_ISL_407987","EPI_ISL_410537","EPI_ISL_416829","EPI_ISL_416866","EPI_ISL_416884"],"id":"H17"},{"haps":["EPI_ISL_416399"],"id":"H125"},{"haps":["EPI_ISL_417666","EPI_ISL_417667"],"id":"H188"},{"id":"H117","haps":["EPI_ISL_416024","EPI_ISL_416739","EPI_ISL_417239","EPI_ISL_417286","EPI_ISL_417604","EPI_ISL_417627","EPI_ISL_417628","EPI_ISL_417649","EPI_ISL_418000"]},{"haps":["EPI_ISL_410301"],"id":"H23"},{"haps":["EPI_ISL_409067"],"id":"H22"},{"haps":["EPI_ISL_414563"],"id":"H80"},{"id":"H25","haps":["EPI_ISL_411957","EPI_ISL_414684","EPI_ISL_414685","EPI_ISL_414686"]},{"haps":["EPI_ISL_413609","EPI_ISL_413617"],"id":"H55"},{"haps":["EPI_ISL_412969","EPI_ISL_413459","EPI_ISL_416582","EPI_ISL_416587","EPI_ISL_416598","EPI_ISL_416610"],"id":"H33"},{"haps":["EPI_ISL_416604"],"id":"H145"},{"haps":["EPI_ISL_416565","EPI_ISL_416603","EPI_ISL_416613","EPI_ISL_416619","EPI_ISL_416624"],"id":"H142"},{"id":"H147","haps":["EPI_ISL_416625"]},{"haps":["EPI_ISL_406534","EPI_ISL_406594","EPI_ISL_408008","EPI_ISL_408009","EPI_ISL_413014","EPI_ISL_413015","EPI_ISL_416365"],"id":"H9"},{"id":"H8","haps":["EPI_ISL_406533","EPI_ISL_408669","EPI_ISL_412966","EPI_ISL_413864","EPI_ISL_414511","EPI_ISL_416361","EPI_ISL_416363","EPI_ISL_416387"]},{"haps":["EPI_ISL_414537","EPI_ISL_414539"],"id":"H73"},{"id":"H123","haps":["EPI_ISL_416389"]},{"id":"H68","haps":["EPI_ISL_414482","EPI_ISL_416570"]},{"haps":["EPI_ISL_414480"],"id":"H67"},{"id":"H21","haps":["EPI_ISL_408482","EPI_ISL_412975","EPI_ISL_412981","EPI_ISL_413490","EPI_ISL_413600","EPI_ISL_414008","EPI_ISL_414476","EPI_ISL_414591","EPI_ISL_415581","EPI_ISL_416373","EPI_ISL_416382","EPI_ISL_416542","EPI_ISL_417238","EPI_ISL_417384","EPI_ISL_417385"]},{"haps":["EPI_ISL_413214","EPI_ISL_414414","EPI_ISL_417386"],"id":"H43"},{"id":"I149"},{"id":"H42","haps":["EPI_ISL_413213","EPI_ISL_413595","EPI_ISL_413597","EPI_ISL_413598","EPI_ISL_415644","EPI_ISL_416412","EPI_ISL_416458","EPI_ISL_416541","EPI_ISL_416543","EPI_ISL_417387","EPI_ISL_417484"]},{"haps":["EPI_ISL_417444"],"id":"H173"},{"haps":["EPI_ISL_414558"],"id":"H78"},{"haps":["EPI_ISL_417413"],"id":"H171"},{"haps":["EPI_ISL_416406","EPI_ISL_416407"],"id":"H126"},{"id":"H70","haps":["EPI_ISL_414520","EPI_ISL_414522","EPI_ISL_417523","EPI_ISL_417524"]},{"haps":["EPI_ISL_416331","EPI_ISL_416332"],"id":"H121"},{"haps":["EPI_ISL_415741","EPI_ISL_415743","EPI_ISL_417519","EPI_ISL_417520","EPI_ISL_417521"],"id":"H115"},{"id":"I145"},{"haps":["EPI_ISL_415742"],"id":"H116"},{"id":"I144"},{"id":"H170","haps":["EPI_ISL_417406"]},{"id":"H53","haps":["EPI_ISL_413599","EPI_ISL_417383","EPI_ISL_417389","EPI_ISL_417391","EPI_ISL_417392","EPI_ISL_417393","EPI_ISL_417398"]},{"id":"H14","haps":["EPI_ISL_406862","EPI_ISL_414640","EPI_ISL_416327","EPI_ISL_416334","EPI_ISL_416386","EPI_ISL_417471","EPI_ISL_417494"]},{"id":"H32","haps":["EPI_ISL_412964","EPI_ISL_412971","EPI_ISL_412973","EPI_ISL_413555","EPI_ISL_413566","EPI_ISL_413575","EPI_ISL_413591","EPI_ISL_413602","EPI_ISL_414015","EPI_ISL_414016","EPI_ISL_414025","EPI_ISL_414045","EPI_ISL_414437","EPI_ISL_414441","EPI_ISL_414443","EPI_ISL_414445","EPI_ISL_414450","EPI_ISL_414453","EPI_ISL_414456","EPI_ISL_414457","EPI_ISL_414465","EPI_ISL_414477","EPI_ISL_414495","EPI_ISL_414525","EPI_ISL_414530","EPI_ISL_414585","EPI_ISL_414586","EPI_ISL_414587","EPI_ISL_414594","EPI_ISL_414631","EPI_ISL_414648","EPI_ISL_414949","EPI_ISL_415131","EPI_ISL_415133","EPI_ISL_415135","EPI_ISL_415136","EPI_ISL_415140","EPI_ISL_415146","EPI_ISL_415147","EPI_ISL_415150","EPI_ISL_415152","EPI_ISL_415156","EPI_ISL_415435","EPI_ISL_415453","EPI_ISL_415472","EPI_ISL_415480","EPI_ISL_415536","EPI_ISL_415601","EPI_ISL_415629","EPI_ISL_415637","EPI_ISL_415639","EPI_ISL_415642","EPI_ISL_415647","EPI_ISL_415653","EPI_ISL_415655","EPI_ISL_415696","EPI_ISL_415708","EPI_ISL_415978","EPI_ISL_416026","EPI_ISL_416031","EPI_ISL_416141","EPI_ISL_416144","EPI_ISL_416420","EPI_ISL_416470","EPI_ISL_416524","EPI_ISL_416525","EPI_ISL_416658","EPI_ISL_416673","EPI_ISL_416735","EPI_ISL_416742","EPI_ISL_416832","EPI_ISL_417013","EPI_ISL_417024","EPI_ISL_417026","EPI_ISL_417027","EPI_ISL_417032","EPI_ISL_417186","EPI_ISL_417198","EPI_ISL_417202","EPI_ISL_417214","EPI_ISL_417220","EPI_ISL_417221","EPI_ISL_417222","EPI_ISL_417223","EPI_ISL_417224","EPI_ISL_417227","EPI_ISL_417228","EPI_ISL_417237","EPI_ISL_417245","EPI_ISL_417247","EPI_ISL_417251","EPI_ISL_417257","EPI_ISL_417266","EPI_ISL_417304","EPI_ISL_417310","EPI_ISL_417397","EPI_ISL_417418","EPI_ISL_417419","EPI_ISL_417421","EPI_ISL_417423","EPI_ISL_417430","EPI_ISL_417434","EPI_ISL_417441","EPI_ISL_417445","EPI_ISL_417446","EPI_ISL_417447","EPI_ISL_417470","EPI_ISL_417472","EPI_ISL_417473","EPI_ISL_417479","EPI_ISL_417481","EPI_ISL_417493","EPI_ISL_417495","EPI_ISL_417496","EPI_ISL_417502","EPI_ISL_417515","EPI_ISL_417535","EPI_ISL_417572","EPI_ISL_417592","EPI_ISL_417638","EPI_ISL_417691","EPI_ISL_417708","EPI_ISL_417727","EPI_ISL_417730","EPI_ISL_417821","EPI_ISL_417831","EPI_ISL_417921","EPI_ISL_417941","EPI_ISL_417959","EPI_ISL_417972","EPI_ISL_417973","EPI_ISL_417974","EPI_ISL_417990","EPI_ISL_418017","EPI_ISL_418116","EPI_ISL_418122","EPI_ISL_418138","EPI_ISL_418139","EPI_ISL_418152","EPI_ISL_418166","EPI_ISL_418210","EPI_ISL_418211","EPI_ISL_418212","EPI_ISL_418213","EPI_ISL_418214","EPI_ISL_418215"]},{"haps":["EPI_ISL_416482","EPI_ISL_417233","EPI_ISL_417248","EPI_ISL_417301","EPI_ISL_417302","EPI_ISL_417695","EPI_ISL_417698","EPI_ISL_417736","EPI_ISL_417749","EPI_ISL_417997","EPI_ISL_417998","EPI_ISL_417999","EPI_ISL_418003"],"id":"H136"},{"haps":["EPI_ISL_414559"],"id":"H79"},{"haps":["EPI_ISL_415462","EPI_ISL_415488","EPI_ISL_415518","EPI_ISL_415520","EPI_ISL_417582","EPI_ISL_417641"],"id":"H99"},{"haps":["EPI_ISL_415535","EPI_ISL_417617","EPI_ISL_417622","EPI_ISL_417706","EPI_ISL_417743","EPI_ISL_417804","EPI_ISL_417823","EPI_ISL_417837"],"id":"H104"},{"id":"H180","haps":["EPI_ISL_417565","EPI_ISL_417637","EPI_ISL_417646","EPI_ISL_417651","EPI_ISL_417839"]},{"haps":["EPI_ISL_414629","EPI_ISL_415651","EPI_ISL_415652","EPI_ISL_415694","EPI_ISL_415695","EPI_ISL_415704","EPI_ISL_415705","EPI_ISL_415706","EPI_ISL_415707","EPI_ISL_416493","EPI_ISL_416499","EPI_ISL_416500","EPI_ISL_416745","EPI_ISL_416747","EPI_ISL_416749","EPI_ISL_416750","EPI_ISL_416751","EPI_ISL_416752","EPI_ISL_416754","EPI_ISL_416756","EPI_ISL_416757","EPI_ISL_417333","EPI_ISL_417334","EPI_ISL_417337","EPI_ISL_417339","EPI_ISL_417437","EPI_ISL_417438","EPI_ISL_417442","EPI_ISL_417526","EPI_ISL_417527","EPI_ISL_417942","EPI_ISL_417946","EPI_ISL_417947","EPI_ISL_418024","EPI_ISL_418230","EPI_ISL_418231","EPI_ISL_418234","EPI_ISL_418240"],"id":"H88"},{"id":"H175","haps":["EPI_ISL_417534"]},{"haps":["EPI_ISL_418222"],"id":"H207"},{"id":"H62","haps":["EPI_ISL_413999","EPI_ISL_414010","EPI_ISL_414027","EPI_ISL_414524","EPI_ISL_414646","EPI_ISL_416741","EPI_ISL_417016","EPI_ISL_417019","EPI_ISL_417424","EPI_ISL_417491","EPI_ISL_417550","EPI_ISL_417560","EPI_ISL_417563","EPI_ISL_417652","EPI_ISL_417694","EPI_ISL_417740","EPI_ISL_417746","EPI_ISL_417758","EPI_ISL_417763","EPI_ISL_417775","EPI_ISL_417799","EPI_ISL_417812","EPI_ISL_417948","EPI_ISL_417955","EPI_ISL_417989"]},{"haps":["EPI_ISL_417877"],"id":"H197"},{"haps":["EPI_ISL_414523","EPI_ISL_414526","EPI_ISL_415134","EPI_ISL_415141","EPI_ISL_416731","EPI_ISL_417217","EPI_ISL_417226","EPI_ISL_417231","EPI_ISL_417240","EPI_ISL_417255","EPI_ISL_417589","EPI_ISL_417754"],"id":"H71"},{"id":"H91","haps":["EPI_ISL_415153","EPI_ISL_416143"]},{"id":"H120","haps":["EPI_ISL_416153"]},{"haps":["EPI_ISL_415155"],"id":"H93"},{"id":"H92","haps":["EPI_ISL_415154","EPI_ISL_416469"]},{"haps":["EPI_ISL_413489","EPI_ISL_413996","EPI_ISL_414601","EPI_ISL_414624","EPI_ISL_416494","EPI_ISL_417529","EPI_ISL_417530","EPI_ISL_417533","EPI_ISL_417569","EPI_ISL_417610","EPI_ISL_417711","EPI_ISL_417764","EPI_ISL_417803","EPI_ISL_417851"],"id":"H46"},{"id":"H31","haps":["EPI_ISL_412912","EPI_ISL_412972","EPI_ISL_413021","EPI_ISL_413022","EPI_ISL_413221","EPI_ISL_413550","EPI_ISL_413556","EPI_ISL_413565","EPI_ISL_413569","EPI_ISL_413570","EPI_ISL_413571","EPI_ISL_413574","EPI_ISL_413579","EPI_ISL_413587","EPI_ISL_414012","EPI_ISL_414023","EPI_ISL_414424","EPI_ISL_414425","EPI_ISL_414434","EPI_ISL_414436","EPI_ISL_414438","EPI_ISL_414440","EPI_ISL_414442","EPI_ISL_414444","EPI_ISL_414448","EPI_ISL_414449","EPI_ISL_414454","EPI_ISL_414455","EPI_ISL_414460","EPI_ISL_414463","EPI_ISL_414464","EPI_ISL_414466","EPI_ISL_414469","EPI_ISL_414470","EPI_ISL_414471","EPI_ISL_414486","EPI_ISL_414488","EPI_ISL_414507","EPI_ISL_414535","EPI_ISL_414548","EPI_ISL_414556","EPI_ISL_414560","EPI_ISL_414566","EPI_ISL_414580","EPI_ISL_414584","EPI_ISL_414644","EPI_ISL_415041","EPI_ISL_415129","EPI_ISL_415138","EPI_ISL_415145","EPI_ISL_415454","EPI_ISL_415457","EPI_ISL_415459","EPI_ISL_415476","EPI_ISL_415532","EPI_ISL_415632","EPI_ISL_415633","EPI_ISL_415634","EPI_ISL_415635","EPI_ISL_415636","EPI_ISL_415656","EPI_ISL_415698","EPI_ISL_415699","EPI_ISL_415700","EPI_ISL_415703","EPI_ISL_415787","EPI_ISL_415916","EPI_ISL_415977","EPI_ISL_415991","EPI_ISL_416036","EPI_ISL_416140","EPI_ISL_416142","EPI_ISL_416428","EPI_ISL_416430","EPI_ISL_416431","EPI_ISL_416472","EPI_ISL_416519","EPI_ISL_416520","EPI_ISL_416676","EPI_ISL_416697","EPI_ISL_416732","EPI_ISL_416734","EPI_ISL_416736","EPI_ISL_416737","EPI_ISL_416743","EPI_ISL_416997","EPI_ISL_417004","EPI_ISL_417012","EPI_ISL_417015","EPI_ISL_417196","EPI_ISL_417225","EPI_ISL_417229","EPI_ISL_417230","EPI_ISL_417241","EPI_ISL_417242","EPI_ISL_417243","EPI_ISL_417244","EPI_ISL_417249","EPI_ISL_417250","EPI_ISL_417258","EPI_ISL_417260","EPI_ISL_417265","EPI_ISL_417271","EPI_ISL_417273","EPI_ISL_417274","EPI_ISL_417278","EPI_ISL_417294","EPI_ISL_417297","EPI_ISL_417307","EPI_ISL_417308","EPI_ISL_417309","EPI_ISL_417311","EPI_ISL_417362","EPI_ISL_417407","EPI_ISL_417422","EPI_ISL_417425","EPI_ISL_417428","EPI_ISL_417458","EPI_ISL_417464","EPI_ISL_417509","EPI_ISL_417525","EPI_ISL_417538","EPI_ISL_417539","EPI_ISL_417546","EPI_ISL_417547","EPI_ISL_417564","EPI_ISL_417567","EPI_ISL_417581","EPI_ISL_417585","EPI_ISL_417595","EPI_ISL_417608","EPI_ISL_417619","EPI_ISL_417642","EPI_ISL_417643","EPI_ISL_417662","EPI_ISL_417663","EPI_ISL_417664","EPI_ISL_417674","EPI_ISL_417679","EPI_ISL_417697","EPI_ISL_417718","EPI_ISL_417729","EPI_ISL_417733","EPI_ISL_417738","EPI_ISL_417747","EPI_ISL_417751","EPI_ISL_417768","EPI_ISL_417769","EPI_ISL_417776","EPI_ISL_417781","EPI_ISL_417782","EPI_ISL_417783","EPI_ISL_417796","EPI_ISL_417807","EPI_ISL_417811","EPI_ISL_417813","EPI_ISL_417826","EPI_ISL_417843","EPI_ISL_417845","EPI_ISL_417922","EPI_ISL_417933","EPI_ISL_417993","EPI_ISL_418002","EPI_ISL_418004","EPI_ISL_418007","EPI_ISL_418008","EPI_ISL_418018","EPI_ISL_418019","EPI_ISL_418023","EPI_ISL_418056","EPI_ISL_418086","EPI_ISL_418087","EPI_ISL_418088","EPI_ISL_418089","EPI_ISL_418090","EPI_ISL_418091","EPI_ISL_418093","EPI_ISL_418094","EPI_ISL_418096","EPI_ISL_418114","EPI_ISL_418118","EPI_ISL_418167"]},{"id":"H49","haps":["EPI_ISL_413584","EPI_ISL_413604","EPI_ISL_413647","EPI_ISL_414014","EPI_ISL_414017","EPI_ISL_414423","EPI_ISL_414433","EPI_ISL_414435","EPI_ISL_414439","EPI_ISL_414446","EPI_ISL_414552","EPI_ISL_414564","EPI_ISL_414643","EPI_ISL_415463","EPI_ISL_415471","EPI_ISL_415482","EPI_ISL_415496","EPI_ISL_415502","EPI_ISL_415514","EPI_ISL_415523","EPI_ISL_415529","EPI_ISL_415533","EPI_ISL_416028","EPI_ISL_416475","EPI_ISL_416730","EPI_ISL_416746","EPI_ISL_417014","EPI_ISL_417232","EPI_ISL_417235","EPI_ISL_417236","EPI_ISL_417252","EPI_ISL_417272","EPI_ISL_417287","EPI_ISL_417293","EPI_ISL_417295","EPI_ISL_417426","EPI_ISL_417427","EPI_ISL_417429","EPI_ISL_417571","EPI_ISL_417575","EPI_ISL_417681","EPI_ISL_417702","EPI_ISL_417728","EPI_ISL_417734","EPI_ISL_417817","EPI_ISL_417829","EPI_ISL_417841","EPI_ISL_417861","EPI_ISL_417863","EPI_ISL_417867","EPI_ISL_417868","EPI_ISL_417986"]},{"id":"I239"},{"haps":["EPI_ISL_417800"],"id":"H194"},{"haps":["EPI_ISL_417704","EPI_ISL_417815","EPI_ISL_417860"],"id":"H190"},{"id":"H65","haps":["EPI_ISL_414429","EPI_ISL_415467","EPI_ISL_415483","EPI_ISL_415498","EPI_ISL_417644","EPI_ISL_417684","EPI_ISL_417688","EPI_ISL_417828","EPI_ISL_417834","EPI_ISL_417840","EPI_ISL_417862"]},{"id":"H74","haps":["EPI_ISL_414545","EPI_ISL_414557","EPI_ISL_414561","EPI_ISL_414562"]},{"haps":["EPI_ISL_416468"],"id":"H133"},{"id":"H95","haps":["EPI_ISL_415158","EPI_ISL_416471"]},{"haps":["EPI_ISL_414554","EPI_ISL_414641","EPI_ISL_415468","EPI_ISL_415497","EPI_ISL_415511","EPI_ISL_415530"],"id":"H76"},{"haps":["EPI_ISL_417852"],"id":"H195"},{"id":"H181","haps":["EPI_ISL_417566","EPI_ISL_417632","EPI_ISL_417713","EPI_ISL_417714","EPI_ISL_417757","EPI_ISL_417785","EPI_ISL_417795","EPI_ISL_417802","EPI_ISL_417876"]},{"id":"H114","haps":["EPI_ISL_415702"]},{"id":"H119","haps":["EPI_ISL_416034"]},{"id":"H161","haps":["EPI_ISL_417234","EPI_ISL_417256","EPI_ISL_417279","EPI_ISL_417343"]},{"id":"H101","haps":["EPI_ISL_415475"]},{"haps":["EPI_ISL_416476"],"id":"H134"},{"id":"H94","haps":["EPI_ISL_415157"]},{"haps":["EPI_ISL_416467"],"id":"H132"},{"id":"H203","haps":["EPI_ISL_417994","EPI_ISL_418011","EPI_ISL_418014","EPI_ISL_418015","EPI_ISL_418016"]},{"id":"H40","haps":["EPI_ISL_413024","EPI_ISL_413997","EPI_ISL_414021","EPI_ISL_414022","EPI_ISL_415455","EPI_ISL_415456","EPI_ISL_415701","EPI_ISL_416744","EPI_ISL_417390","EPI_ISL_417551","EPI_ISL_417816"]},{"haps":["EPI_ISL_414549"],"id":"H75"},{"haps":["EPI_ISL_417191"],"id":"H160"},{"id":"H209","haps":["EPI_ISL_418235"]},{"id":"H38","haps":["EPI_ISL_413020","EPI_ISL_416486","EPI_ISL_417298","EPI_ISL_417299","EPI_ISL_417992","EPI_ISL_417995","EPI_ISL_418001","EPI_ISL_418013"]},{"id":"H39","haps":["EPI_ISL_413023","EPI_ISL_415105","EPI_ISL_415458","EPI_ISL_416029","EPI_ISL_416035","EPI_ISL_417404","EPI_ISL_417512","EPI_ISL_417561","EPI_ISL_418043"]},{"id":"H156","haps":["EPI_ISL_417021","EPI_ISL_417022","EPI_ISL_417023"]},{"id":"H100","haps":["EPI_ISL_415473","EPI_ISL_415474","EPI_ISL_415485","EPI_ISL_415499"]},{"id":"H211","haps":["EPI_ISL_418251"]},{"id":"H63","haps":["EPI_ISL_414019","EPI_ISL_414020","EPI_ISL_416426","EPI_ISL_416481","EPI_ISL_417007","EPI_ISL_417010","EPI_ISL_417402","EPI_ISL_417639","EPI_ISL_417814","EPI_ISL_417820","EPI_ISL_417923","EPI_ISL_417954","EPI_ISL_417963","EPI_ISL_417978","EPI_ISL_418168","EPI_ISL_418183"]},{"haps":["EPI_ISL_417536","EPI_ISL_417537","EPI_ISL_417542","EPI_ISL_417543","EPI_ISL_417549","EPI_ISL_417552","EPI_ISL_417573","EPI_ISL_417583","EPI_ISL_417586","EPI_ISL_417588","EPI_ISL_417597","EPI_ISL_417599","EPI_ISL_417600","EPI_ISL_417612","EPI_ISL_417613","EPI_ISL_417623","EPI_ISL_417625","EPI_ISL_417626","EPI_ISL_417630","EPI_ISL_417633","EPI_ISL_417634","EPI_ISL_417635","EPI_ISL_417636","EPI_ISL_417640","EPI_ISL_417645","EPI_ISL_417650","EPI_ISL_417676","EPI_ISL_417678","EPI_ISL_417680","EPI_ISL_417703","EPI_ISL_417709","EPI_ISL_417712","EPI_ISL_417739","EPI_ISL_417741","EPI_ISL_417745","EPI_ISL_417753","EPI_ISL_417755","EPI_ISL_417774","EPI_ISL_417786","EPI_ISL_417790","EPI_ISL_417808","EPI_ISL_417809","EPI_ISL_417810","EPI_ISL_417824","EPI_ISL_417827","EPI_ISL_417836"],"id":"H176"},{"haps":["EPI_ISL_417609","EPI_ISL_417647","EPI_ISL_417956"],"id":"H184"},{"haps":["EPI_ISL_417957","EPI_ISL_418182"],"id":"H199"},{"haps":["EPI_ISL_417744"],"id":"H191"},{"id":"H137","haps":["EPI_ISL_416489","EPI_ISL_417967"]},{"haps":["EPI_ISL_418009"],"id":"H204"},{"haps":["EPI_ISL_417969"],"id":"H200"},{"id":"H193","haps":["EPI_ISL_417766","EPI_ISL_417770","EPI_ISL_417777","EPI_ISL_417798"]},{"haps":["EPI_ISL_413593","EPI_ISL_415640","EPI_ISL_415646","EPI_ISL_417485","EPI_ISL_417556"],"id":"H52"},{"haps":["EPI_ISL_413648","EPI_ISL_417987","EPI_ISL_417988","EPI_ISL_417991","EPI_ISL_417996","EPI_ISL_418010","EPI_ISL_418012"],"id":"H57"},{"haps":["EPI_ISL_416479"],"id":"H135"},{"id":"H64","haps":["EPI_ISL_414428"]},{"id":"H97","haps":["EPI_ISL_415460","EPI_ISL_415465","EPI_ISL_415466","EPI_ISL_415469","EPI_ISL_415515","EPI_ISL_415525","EPI_ISL_415534"]},{"haps":["EPI_ISL_417420"],"id":"H172"},{"id":"I231"},{"haps":["EPI_ISL_414626","EPI_ISL_414632","EPI_ISL_414633","EPI_ISL_414637","EPI_ISL_414638","EPI_ISL_415654","EPI_ISL_415697","EPI_ISL_416497","EPI_ISL_417411","EPI_ISL_417440","EPI_ISL_417517","EPI_ISL_417648","EPI_ISL_417878","EPI_ISL_418035","EPI_ISL_418223","EPI_ISL_418225","EPI_ISL_418227","EPI_ISL_418238"],"id":"H86"},{"id":"H198","haps":["EPI_ISL_417879","EPI_ISL_418229","EPI_ISL_418232","EPI_ISL_418233"]},{"haps":["EPI_ISL_413572","EPI_ISL_414625","EPI_ISL_414627","EPI_ISL_414634","EPI_ISL_414635","EPI_ISL_414636","EPI_ISL_414642","EPI_ISL_415477","EPI_ISL_415487","EPI_ISL_415543","EPI_ISL_415544","EPI_ISL_415649","EPI_ISL_415650","EPI_ISL_415692","EPI_ISL_415693","EPI_ISL_416457","EPI_ISL_416478","EPI_ISL_416491","EPI_ISL_416492","EPI_ISL_416495","EPI_ISL_416496","EPI_ISL_416501","EPI_ISL_416502","EPI_ISL_416504","EPI_ISL_416505","EPI_ISL_416506","EPI_ISL_416508","EPI_ISL_416509","EPI_ISL_416510","EPI_ISL_416511","EPI_ISL_416512","EPI_ISL_416642","EPI_ISL_416655","EPI_ISL_416660","EPI_ISL_416672","EPI_ISL_416678","EPI_ISL_416704","EPI_ISL_416748","EPI_ISL_416753","EPI_ISL_416830","EPI_ISL_417006","EPI_ISL_417020","EPI_ISL_417204","EPI_ISL_417330","EPI_ISL_417338","EPI_ISL_417340","EPI_ISL_417352","EPI_ISL_417359","EPI_ISL_417373","EPI_ISL_417457","EPI_ISL_417463","EPI_ISL_417465","EPI_ISL_417466","EPI_ISL_417467","EPI_ISL_417468","EPI_ISL_417469","EPI_ISL_417474","EPI_ISL_417476","EPI_ISL_417492","EPI_ISL_417497","EPI_ISL_417499","EPI_ISL_417505","EPI_ISL_417516","EPI_ISL_417559","EPI_ISL_417562","EPI_ISL_417570","EPI_ISL_417579","EPI_ISL_417593","EPI_ISL_417594","EPI_ISL_417596","EPI_ISL_417614","EPI_ISL_417620","EPI_ISL_417631","EPI_ISL_417654","EPI_ISL_417656","EPI_ISL_417665","EPI_ISL_417673","EPI_ISL_417675","EPI_ISL_417677","EPI_ISL_417682","EPI_ISL_417683","EPI_ISL_417685","EPI_ISL_417687","EPI_ISL_417692","EPI_ISL_417693","EPI_ISL_417700","EPI_ISL_417701","EPI_ISL_417705","EPI_ISL_417715","EPI_ISL_417721","EPI_ISL_417722","EPI_ISL_417723","EPI_ISL_417725","EPI_ISL_417726","EPI_ISL_417731","EPI_ISL_417735","EPI_ISL_417742","EPI_ISL_417748","EPI_ISL_417760","EPI_ISL_417761","EPI_ISL_417773","EPI_ISL_417779","EPI_ISL_417784","EPI_ISL_417787","EPI_ISL_417805","EPI_ISL_417832","EPI_ISL_417833","EPI_ISL_417835","EPI_ISL_417842","EPI_ISL_417844","EPI_ISL_417846","EPI_ISL_417848","EPI_ISL_417849","EPI_ISL_417850","EPI_ISL_417853","EPI_ISL_417854","EPI_ISL_417855","EPI_ISL_417856","EPI_ISL_417857","EPI_ISL_417865","EPI_ISL_417866","EPI_ISL_417872","EPI_ISL_417873","EPI_ISL_417874","EPI_ISL_417875","EPI_ISL_417935","EPI_ISL_417937","EPI_ISL_417938","EPI_ISL_417939","EPI_ISL_417970","EPI_ISL_417977","EPI_ISL_418022","EPI_ISL_418041","EPI_ISL_418044","EPI_ISL_418057","EPI_ISL_418058","EPI_ISL_418076","EPI_ISL_418095","EPI_ISL_418097","EPI_ISL_418098","EPI_ISL_418109","EPI_ISL_418119","EPI_ISL_418184","EPI_ISL_418188","EPI_ISL_418190","EPI_ISL_418192","EPI_ISL_418193","EPI_ISL_418196","EPI_ISL_418197","EPI_ISL_418198","EPI_ISL_418199","EPI_ISL_418200","EPI_ISL_418202","EPI_ISL_418203","EPI_ISL_418204","EPI_ISL_418218","EPI_ISL_418220","EPI_ISL_418221","EPI_ISL_418226","EPI_ISL_418228","EPI_ISL_418236","EPI_ISL_418239"],"id":"H47"},{"id":"H208","haps":["EPI_ISL_418224"]},{"id":"H205","haps":["EPI_ISL_418039"]},{"id":"H96","haps":["EPI_ISL_415159"]},{"id":"H169","haps":["EPI_ISL_417376","EPI_ISL_417971","EPI_ISL_418028","EPI_ISL_418036","EPI_ISL_418042","EPI_ISL_418049","EPI_ISL_418051"]},{"id":"H150","haps":["EPI_ISL_416661","EPI_ISL_417345","EPI_ISL_417932","EPI_ISL_418037","EPI_ISL_418072"]},{"haps":["EPI_ISL_415481"],"id":"H102"},{"haps":["EPI_ISL_414630","EPI_ISL_416498","EPI_ISL_418237","EPI_ISL_418241","EPI_ISL_418242"],"id":"H89"},{"haps":["EPI_ISL_417531","EPI_ISL_417532"],"id":"H174"},{"id":"H187","haps":["EPI_ISL_417629","EPI_ISL_417806","EPI_ISL_418206","EPI_ISL_418207","EPI_ISL_418208","EPI_ISL_418209"]},{"haps":["EPI_ISL_417752"],"id":"H192"},{"haps":["EPI_ISL_417976"],"id":"H201"},{"id":"H84","haps":["EPI_ISL_414616","EPI_ISL_415597","EPI_ISL_415625","EPI_ISL_416434","EPI_ISL_416438","EPI_ISL_416452","EPI_ISL_416647","EPI_ISL_416648","EPI_ISL_416653","EPI_ISL_416691","EPI_ISL_416693","EPI_ISL_416698","EPI_ISL_416699","EPI_ISL_416707","EPI_ISL_416708","EPI_ISL_416716","EPI_ISL_416719","EPI_ISL_416724","EPI_ISL_416725","EPI_ISL_416729","EPI_ISL_417341","EPI_ISL_417342","EPI_ISL_417379","EPI_ISL_417382","EPI_ISL_417451","EPI_ISL_417454","EPI_ISL_417455","EPI_ISL_417690","EPI_ISL_418032","EPI_ISL_418033","EPI_ISL_418053","EPI_ISL_418054","EPI_ISL_418067","EPI_ISL_418068","EPI_ISL_418073","EPI_ISL_418081"]},{"haps":["EPI_ISL_417555","EPI_ISL_417797"],"id":"H179"},{"id":"H112","haps":["EPI_ISL_415648"]},{"id":"H138","haps":["EPI_ISL_416513"]},{"haps":["EPI_ISL_416523","EPI_ISL_417598","EPI_ISL_417830"],"id":"H139"},{"haps":["EPI_ISL_414628","EPI_ISL_414647","EPI_ISL_415710","EPI_ISL_416517","EPI_ISL_416758","EPI_ISL_417336","EPI_ISL_418219"],"id":"H87"},{"id":"I201"},{"id":"I200"},{"haps":["EPI_ISL_414936","EPI_ISL_414937","EPI_ISL_414938","EPI_ISL_414939","EPI_ISL_414940","EPI_ISL_414941"],"id":"H90"},{"haps":["EPI_ISL_417689"],"id":"H189"},{"haps":["EPI_ISL_417624","EPI_ISL_417737","EPI_ISL_417788","EPI_ISL_417819"],"id":"H186"},{"id":"H51","haps":["EPI_ISL_413592","EPI_ISL_416521","EPI_ISL_416522","EPI_ISL_416671","EPI_ISL_416674","EPI_ISL_416831","EPI_ISL_417192","EPI_ISL_417372","EPI_ISL_417452","EPI_ISL_417506","EPI_ISL_417508","EPI_ISL_417510","EPI_ISL_417513","EPI_ISL_417944","EPI_ISL_418006"]},{"haps":["EPI_ISL_417018"],"id":"H155"},{"id":"H50","haps":["EPI_ISL_413588","EPI_ISL_413589","EPI_ISL_414461"]}],[{"change":[{"src_aa":"L","tgt_aa":"F","tgt_base":"T","site":"11083","pos":10818,"src_codon":"ttg","label":"orf1ab","cd_pos":3,"tgt_codon":"ttt","src_base":"G"}],"id":"H2-H7","target":"H7","source":"H2"},{"source":"H7","target":"H20","change":[{"site":"29095","src_aa":"F","tgt_aa":"F","tgt_base":"C","src_codon":"ttt","label":"N","cd_pos":3,"tgt_codon":"ttc","src_base":"T","pos":822}],"id":"H7-H20"},{"id":"H20-H13","change":[{"tgt_aa":"L","src_aa":"F","tgt_base":"G","site":"11083","pos":10818,"src_codon":"ttt","label":"orf1ab","tgt_codon":"ttg","cd_pos":3,"src_base":"T"}],"target":"H13","source":"H20"},{"target":"H122","source":"H13","id":"H13-H122","change":[{"src_base":"T","cd_pos":2,"label":"orf1ab","tgt_codon":"tat","src_codon":"ttt","pos":9212,"site":"9477","tgt_base":"A","tgt_aa":"Y","src_aa":"F"}]},{"source":"H122","target":"H202","change":[{"src_base":"C","tgt_codon":"tat","cd_pos":3,"label":"orf1ab","src_codon":"tac","pos":14540,"site":"14805","tgt_base":"T","src_aa":"Y","tgt_aa":"Y"},{"site":"28863","tgt_base":"T","tgt_aa":"L","src_aa":"S","src_base":"C","cd_pos":2,"tgt_codon":"tta","label":"N","src_codon":"tca","pos":590}],"id":"H122-H202"},{"id":"H202-H81","change":[{"site":"25979","tgt_base":"T","tgt_aa":"V","src_aa":"G","src_base":"G","tgt_codon":"gta","label":"ORF3a","cd_pos":2,"src_codon":"gga","pos":587},{"src_aa":"D","tgt_aa":"D","tgt_base":"T","site":"28657","pos":384,"src_codon":"gac","tgt_codon":"gat","label":"N","cd_pos":3,"src_base":"C"}],"target":"H81","source":"H202"},{"source":"H13","target":"H16","id":"H13-H16","change":[{"src_aa":"S","tgt_aa":"N","tgt_base":"A","site":"28878","pos":605,"src_base":"G","src_codon":"agt","label":"N","cd_pos":2,"tgt_codon":"aat"}]},{"target":"H98","source":"H16","change":[{"tgt_base":"A","src_aa":"V","tgt_aa":"I","site":"16381","pos":16116,"src_base":"G","tgt_codon":"att","label":"orf1ab","cd_pos":1,"src_codon":"gtt"}],"id":"H16-H98"},{"target":"H77","source":"H98","id":"H98-H77","change":[{"src_aa":"A","tgt_aa":"V","tgt_base":"T","site":"6255","pos":5990,"src_base":"C","src_codon":"gca","label":"orf1ab","tgt_codon":"gta","cd_pos":2}]},{"id":"H13-H59","change":[{"tgt_base":"T","src_aa":null,"tgt_aa":null,"site":"207","pos":207,"src_base":"C","tgt_codon":null,"label":"5-UTR","cd_pos":null,"src_codon":null},{"src_aa":"G","tgt_aa":"G","tgt_base":"C","site":"946","pos":681,"src_base":"T","src_codon":"ggt","tgt_codon":"ggc","label":"orf1ab","cd_pos":3},{"tgt_base":"G","tgt_aa":"C","src_aa":"Y","site":"11430","pos":11165,"src_base":"A","label":"orf1ab","tgt_codon":"tgt","cd_pos":2,"src_codon":"tat"}],"target":"H59","source":"H13"},{"change":[{"src_codon":"aac","tgt_codon":"aat","label":"S","cd_pos":3,"src_base":"C","pos":"2472","site":"24034","tgt_aa":"N","src_aa":"N","tgt_base":"T"}],"id":"H13-I28","target":"I28","source":"H13"},{"target":"H6","source":"I28","change":[{"site":"26729","src_aa":"A","tgt_aa":"A","tgt_base":"C","src_codon":"gct","label":"M","cd_pos":3,"tgt_codon":"gcc","src_base":"T","pos":"207"},{"site":"28077","tgt_base":"C","src_aa":"V","tgt_aa":"L","src_base":"G","cd_pos":1,"label":"ORF8","tgt_codon":"ctg","src_codon":"gtg","pos":"184"}],"id":"I28-H6"},{"id":"H6-H26","change":[{"src_base":"G","tgt_codon":"ttc","cd_pos":1,"label":"S","src_codon":"gtc","pos":1099,"site":"22661","tgt_base":"T","src_aa":"V","tgt_aa":"F"}],"target":"H26","source":"H6"},{"target":"H140","source":"H6","change":[{"site":"29700","src_aa":null,"tgt_aa":null,"tgt_base":"G","src_base":"A","src_codon":null,"cd_pos":null,"tgt_codon":null,"label":"3-UTR","pos":26}],"id":"H6-H140"},{"source":"I28","target":"H141","id":"I28-H141","change":[{"pos":"26","label":"3-UTR","cd_pos":null,"tgt_codon":null,"src_codon":null,"src_base":"A","tgt_base":"G","src_aa":null,"tgt_aa":null,"site":"29700"}]},{"change":[{"pos":8517,"tgt_codon":"agc","label":"orf1ab","cd_pos":3,"src_codon":"agt","src_base":"T","tgt_base":"C","tgt_aa":"S","src_aa":"S","site":"8782"},{"site":"28144","tgt_base":"T","tgt_aa":"L","src_aa":"S","tgt_codon":"tta","cd_pos":2,"label":"ORF8","src_codon":"tca","src_base":"C","pos":251}],"id":"H13-H1","source":"H13","target":"H1"},{"id":"H1-H48","change":[{"tgt_base":"C","tgt_aa":"H","src_aa":"H","site":"514","pos":249,"src_base":"T","cd_pos":3,"tgt_codon":"cac","label":"orf1ab","src_codon":"cat"}],"source":"H1","target":"H48"},{"source":"H48","target":"H82","change":[{"site":"17410","tgt_base":"T","tgt_aa":"C","src_aa":"R","label":"orf1ab","tgt_codon":"tgt","cd_pos":1,"src_codon":"cgt","src_base":"C","pos":17145}],"id":"H48-H82"},{"target":"H72","source":"H82","id":"H82-H72","change":[{"tgt_base":"T","src_aa":"A","tgt_aa":"V","site":"6255","pos":5990,"cd_pos":2,"label":"orf1ab","tgt_codon":"gta","src_codon":"gca","src_base":"C"}]},{"source":"H1","target":"H188","id":"H1-H188","change":[{"site":"20270","tgt_base":"T","tgt_aa":"V","src_aa":"A","src_base":"C","cd_pos":2,"label":"orf1ab","tgt_codon":"gtt","src_codon":"gct","pos":20005}]},{"change":[{"pos":9,"src_base":"A","src_codon":null,"label":"3-UTR","tgt_codon":null,"cd_pos":null,"src_aa":null,"tgt_aa":null,"tgt_base":"T","site":"29683"}],"id":"H188-H117","source":"H188","target":"H117"},{"source":"H1","target":"I85","id":"H1-I85","change":[{"src_aa":"A","tgt_aa":"T","tgt_base":"A","site":"2891","pos":"2626","src_base":"G","src_codon":"gca","label":"orf1ab","cd_pos":1,"tgt_codon":"aca"},{"tgt_base":"A","src_aa":"G","tgt_aa":"D","site":"1440","pos":"1175","src_base":"G","cd_pos":2,"label":"orf1ab","tgt_codon":"gac","src_codon":"ggc"}]},{"source":"I85","target":"H45","change":[],"id":"I85-H45"},{"target":"H113","source":"I85","change":[{"src_base":"G","src_codon":"agt","cd_pos":2,"label":"N","tgt_codon":"att","pos":"578","site":"28851","src_aa":"S","tgt_aa":"I","tgt_base":"T"}],"id":"I85-H113"},{"change":[{"pos":15059,"src_base":"C","tgt_codon":"aat","label":"orf1ab","cd_pos":3,"src_codon":"aac","tgt_base":"T","src_aa":"N","tgt_aa":"N","site":"15324"},{"pos":1030,"src_base":"C","src_codon":"cca","label":"N","cd_pos":1,"tgt_codon":"tca","src_aa":"P","tgt_aa":"S","tgt_base":"T","site":"29303"}],"id":"H1-H8","target":"H8","source":"H1"},{"change":[{"pos":62,"src_base":"G","label":"3-UTR","cd_pos":null,"tgt_codon":null,"src_codon":null,"tgt_base":"T","src_aa":null,"tgt_aa":null,"site":"29736"}],"id":"H1-H54","target":"H54","source":"H1"},{"id":"H54-H144","change":[{"pos":10818,"src_base":"G","src_codon":"ttg","label":"orf1ab","cd_pos":3,"tgt_codon":"ttt","tgt_aa":"F","src_aa":"L","tgt_base":"T","site":"11083"}],"source":"H54","target":"H144"},{"id":"H144-H68","change":[{"pos":254,"src_base":"C","label":"5-UTR","tgt_codon":null,"cd_pos":null,"src_codon":null,"tgt_base":"T","src_aa":null,"tgt_aa":null,"site":"254"},{"site":"29751","src_aa":null,"tgt_aa":null,"tgt_base":"C","src_codon":null,"cd_pos":null,"label":"3-UTR","tgt_codon":null,"src_base":"G","pos":77}],"target":"H68","source":"H144"},{"change":[{"pos":10818,"cd_pos":3,"label":"orf1ab","tgt_codon":"ttg","src_codon":"ttt","src_base":"T","tgt_base":"G","src_aa":"F","tgt_aa":"L","site":"11083"}],"id":"H68-H67","target":"H67","source":"H68"},{"target":"H18","source":"H144","id":"H144-H18","change":[{"src_aa":null,"tgt_aa":null,"tgt_base":"G","site":"29736","pos":62,"src_codon":null,"label":"3-UTR","tgt_codon":null,"cd_pos":null,"src_base":"T"}]},{"target":"H143","source":"H18","change":[{"src_codon":"ttg","cd_pos":3,"label":"orf1ab","tgt_codon":"tta","src_base":"G","pos":11145,"site":"11410","tgt_aa":"L","src_aa":"L","tgt_base":"A"}],"id":"H18-H143"},{"target":"H129","source":"H18","id":"H18-H129","change":[{"src_codon":"aca","label":"orf1ab","cd_pos":2,"tgt_codon":"aaa","src_base":"C","pos":6047,"site":"6312","tgt_aa":"K","src_aa":"T","tgt_base":"A"},{"pos":13465,"src_base":"C","label":"orf1ab","tgt_codon":"gtt","cd_pos":2,"src_codon":"gct","tgt_base":"T","src_aa":"A","tgt_aa":"V","site":"13730"},{"src_base":"C","src_codon":"tac","label":"S","cd_pos":3,"tgt_codon":"tat","pos":2367,"site":"23929","src_aa":"Y","tgt_aa":"Y","tgt_base":"T"},{"src_codon":"ccc","cd_pos":2,"label":"N","tgt_codon":"ctc","src_base":"C","pos":38,"site":"28311","src_aa":"P","tgt_aa":"L","tgt_base":"T"}]},{"target":"H146","source":"H18","change":[{"site":"8782","tgt_aa":"S","src_aa":"S","tgt_base":"T","src_codon":"agc","cd_pos":3,"label":"orf1ab","tgt_codon":"agt","src_base":"C","pos":8517}],"id":"H18-H146"},{"change":[{"pos":752,"src_base":"G","label":"ORF3a","tgt_codon":"gtt","cd_pos":2,"src_codon":"ggt","tgt_base":"T","src_aa":"G","tgt_aa":"V","site":"26144"}],"id":"H18-H24","source":"H18","target":"H24"},{"change":[{"pos":14540,"src_base":"C","src_codon":"tac","label":"orf1ab","cd_pos":3,"tgt_codon":"tat","tgt_aa":"Y","src_aa":"Y","tgt_base":"T","site":"14805"}],"id":"H24-H41","target":"H41","source":"H24"},{"id":"H41-H36","change":[{"label":"orf1ab","cd_pos":3,"tgt_codon":"cgc","src_codon":"cgt","src_base":"T","pos":16982,"site":"17247","tgt_base":"C","tgt_aa":"R","src_aa":"R"}],"source":"H41","target":"H36"},{"change":[{"site":"3034","tgt_base":"C","tgt_aa":"S","src_aa":"S","cd_pos":3,"label":"orf1ab","tgt_codon":"tcc","src_codon":"tct","src_base":"T","pos":2769},{"site":"16054","tgt_aa":"Y","src_aa":"H","tgt_base":"T","src_base":"C","src_codon":"cat","tgt_codon":"tat","label":"orf1ab","cd_pos":1,"pos":15789},{"tgt_codon":"tac","cd_pos":3,"label":"orf1ab","src_codon":"tat","src_base":"T","pos":17594,"site":"17859","tgt_base":"C","src_aa":"Y","tgt_aa":"Y"},{"src_base":"G","cd_pos":null,"label":"3-UTR","tgt_codon":null,"src_codon":null,"pos":77,"site":"29751","tgt_base":"C","src_aa":null,"tgt_aa":null}],"id":"H36-H177","target":"H177","source":"H36"},{"source":"H36","target":"H111","id":"H36-H111","change":[{"site":"1515","src_aa":"H","tgt_aa":"R","tgt_base":"G","src_codon":"cat","tgt_codon":"cgt","label":"orf1ab","cd_pos":2,"src_base":"A","pos":1250}]},{"source":"H111","target":"H148","change":[{"tgt_aa":"H","src_aa":"H","tgt_base":"T","site":"9223","pos":8958,"src_codon":"cac","label":"orf1ab","cd_pos":3,"tgt_codon":"cat","src_base":"C"}],"id":"H111-H148"},{"target":"H154","source":"H148","change":[{"tgt_codon":"ata","label":"orf1ab","cd_pos":2,"src_codon":"aca","src_base":"C","pos":9173,"site":"9438","tgt_base":"T","tgt_aa":"I","src_aa":"T"}],"id":"H148-H154"},{"change":[{"pos":10818,"src_base":"T","src_codon":"ttt","cd_pos":3,"tgt_codon":"ttg","label":"orf1ab","src_aa":"F","tgt_aa":"L","tgt_base":"G","site":"11083"}],"id":"H154-H157","target":"H157","source":"H154"},{"change":[{"src_codon":"tca","label":"orf1ab","cd_pos":2,"tgt_codon":"tta","src_base":"C","pos":17374,"site":"17639","src_aa":"S","tgt_aa":"L","tgt_base":"T"}],"id":"H36-H206","source":"H36","target":"H206"},{"source":"H36","target":"H178","change":[{"src_codon":"act","label":"orf1ab","tgt_codon":"att","cd_pos":2,"src_base":"C","pos":4877,"site":"5142","src_aa":"T","tgt_aa":"I","tgt_base":"T"}],"id":"H36-H178"},{"target":"H118","source":"H36","id":"H36-H118","change":[{"tgt_base":"G","tgt_aa":"L","src_aa":"F","site":"11083","pos":10818,"tgt_codon":"ttg","label":"orf1ab","cd_pos":3,"src_codon":"ttt","src_base":"T"}]},{"source":"H36","target":"H163","change":[{"tgt_base":"T","src_aa":"L","tgt_aa":"F","site":"21575","pos":13,"src_base":"C","label":"S","cd_pos":1,"tgt_codon":"ttt","src_codon":"ctt"}],"id":"H36-H163"},{"change":[{"pos":1056,"src_base":"A","src_codon":"gaa","cd_pos":3,"label":"orf1ab","tgt_codon":"gac","src_aa":"E","tgt_aa":"D","tgt_base":"C","site":"1321"}],"id":"H36-H183","target":"H183","source":"H36"},{"source":"H36","target":"H103","change":[{"site":"14408","tgt_base":"T","tgt_aa":"L","src_aa":"P","src_base":"C","label":"orf1ab","cd_pos":2,"tgt_codon":"ctt","src_codon":"cct","pos":14143}],"id":"H36-H103"},{"change":[{"pos":2293,"src_base":"C","src_codon":"cca","label":"orf1ab","cd_pos":1,"tgt_codon":"tca","tgt_aa":"S","src_aa":"P","tgt_base":"T","site":"2558"}],"id":"H41-H162","target":"H162","source":"H41"},{"target":"H28","source":"H162","id":"H162-H28","change":[{"tgt_base":"G","tgt_aa":"V","src_aa":"I","site":"2480","pos":2215,"label":"orf1ab","tgt_codon":"gtt","cd_pos":1,"src_codon":"att","src_base":"A"}]},{"change":[{"tgt_base":"C","tgt_aa":"D","src_aa":"D","site":"27384","pos":183,"tgt_codon":"gac","label":"ORF6","cd_pos":3,"src_codon":"gat","src_base":"T"}],"id":"H41-H210","target":"H210","source":"H41"},{"id":"H18-I272","change":[{"src_aa":"F","tgt_aa":"F","tgt_base":"T","site":"3037","pos":"2772","src_base":"C","src_codon":"ttc","label":"orf1ab","cd_pos":3,"tgt_codon":"ttt"}],"source":"H18","target":"I272"},{"target":"H14","source":"I272","id":"I272-H14","change":[{"pos":"241","tgt_codon":null,"label":"5-UTR","cd_pos":null,"src_codon":null,"src_base":"C","tgt_base":"T","tgt_aa":null,"src_aa":null,"site":"241"},{"site":"11083","tgt_base":"G","src_aa":"F","tgt_aa":"L","cd_pos":3,"label":"orf1ab","tgt_codon":"ttg","src_codon":"ttt","src_base":"T","pos":"10818"},{"tgt_aa":"G","src_aa":"D","tgt_base":"G","site":"23403","pos":"1841","src_base":"A","src_codon":"gat","cd_pos":2,"tgt_codon":"ggt","label":"S"}]},{"source":"H14","target":"H32","change":[{"site":"14408","tgt_aa":"L","src_aa":"P","tgt_base":"T","src_codon":"cct","cd_pos":2,"label":"orf1ab","tgt_codon":"ctt","src_base":"C","pos":14143}],"id":"H14-H32"},{"change":[{"site":"24862","tgt_base":"G","tgt_aa":"T","src_aa":"T","src_base":"A","tgt_codon":"acg","label":"S","cd_pos":3,"src_codon":"aca","pos":3300}],"id":"H32-H99","source":"H32","target":"H99"},{"change":[{"site":"658","src_aa":"A","tgt_aa":"A","tgt_base":"C","src_codon":"gct","tgt_codon":"gcc","label":"orf1ab","cd_pos":3,"src_base":"T","pos":393},{"src_base":"C","cd_pos":2,"tgt_codon":"gtt","label":"N","src_codon":"gct","pos":356,"site":"28629","tgt_base":"T","tgt_aa":"V","src_aa":"A"}],"id":"H99-H104","source":"H99","target":"H104"},{"source":"H32","target":"H91","change":[{"tgt_base":"G","src_aa":"Y","tgt_aa":"*","site":"13402","pos":13137,"label":"orf1ab","tgt_codon":"tag","cd_pos":3,"src_codon":"tat","src_base":"T"}],"id":"H32-H91"},{"change":[{"site":"187","tgt_base":"G","src_aa":null,"tgt_aa":null,"label":"5-UTR","tgt_codon":null,"cd_pos":null,"src_codon":null,"src_base":"A","pos":187}],"id":"H91-H120","target":"H120","source":"H91"},{"id":"H91-H93","change":[{"src_aa":"S","tgt_aa":"T","tgt_base":"C","site":"24390","pos":2828,"src_codon":"agt","tgt_codon":"act","label":"S","cd_pos":2,"src_base":"G"}],"target":"H93","source":"H91"},{"source":"H93","target":"H92","id":"H93-H92","change":[{"pos":2827,"src_codon":"agt","cd_pos":1,"label":"S","tgt_codon":"cgt","src_base":"A","src_aa":"S","tgt_aa":"R","tgt_base":"C","site":"24389"}]},{"change":[{"pos":2515,"src_base":"G","tgt_codon":"tat","label":"S","cd_pos":1,"src_codon":"gat","tgt_base":"T","src_aa":"D","tgt_aa":"Y","site":"24077"}],"id":"H32-H136","source":"H32","target":"H136"},{"change":[{"site":"8782","tgt_base":"T","tgt_aa":"S","src_aa":"S","src_base":"C","label":"orf1ab","tgt_codon":"agt","cd_pos":3,"src_codon":"agc","pos":8517}],"id":"H32-H211","source":"H32","target":"H211"},{"target":"H180","source":"H32","id":"H32-H180","change":[{"tgt_base":"T","src_aa":"L","tgt_aa":"L","site":"2455","pos":2190,"cd_pos":3,"tgt_codon":"ctt","label":"orf1ab","src_codon":"ctc","src_base":"C"},{"site":"10450","tgt_aa":"P","src_aa":"P","tgt_base":"T","src_codon":"ccc","label":"orf1ab","tgt_codon":"cct","cd_pos":3,"src_base":"C","pos":10185}]},{"id":"H32-H63","change":[{"src_aa":"L","tgt_aa":"L","tgt_base":"G","site":"20268","pos":20003,"src_base":"A","src_codon":"tta","label":"orf1ab","tgt_codon":"ttg","cd_pos":3}],"source":"H32","target":"H63"},{"change":[{"cd_pos":2,"label":"N","tgt_codon":"tta","src_codon":"tca","src_base":"C","pos":581,"site":"28854","tgt_base":"T","src_aa":"S","tgt_aa":"L"}],"id":"H63-H193","source":"H63","target":"H193"},{"id":"H63-H184","change":[{"pos":60,"src_base":"G","cd_pos":null,"label":"3-UTR","tgt_codon":null,"src_codon":null,"tgt_base":"C","src_aa":null,"tgt_aa":null,"site":"29734"}],"source":"H63","target":"H184"},{"id":"H184-H199","change":[{"tgt_codon":"tat","label":"orf1ab","cd_pos":3,"src_codon":"tac","src_base":"C","pos":11439,"site":"11704","tgt_base":"T","src_aa":"Y","tgt_aa":"Y"}],"target":"H199","source":"H184"},{"source":"H63","target":"H191","id":"H63-H191","change":[{"site":"3037","src_aa":"F","tgt_aa":"F","tgt_base":"C","src_codon":"ttt","tgt_codon":"ttc","cd_pos":3,"label":"orf1ab","src_base":"T","pos":2772}]},{"target":"H137","source":"H63","id":"H63-H137","change":[{"site":"17639","tgt_base":"T","tgt_aa":"L","src_aa":"S","src_base":"C","label":"orf1ab","cd_pos":2,"tgt_codon":"tta","src_codon":"tca","pos":17374}]},{"source":"H137","target":"H204","id":"H137-H204","change":[{"pos":26,"src_codon":null,"cd_pos":null,"label":"3-UTR","tgt_codon":null,"src_base":"A","tgt_aa":null,"src_aa":null,"tgt_base":"G","site":"29700"}]},{"change":[{"pos":14143,"src_codon":"ctt","label":"orf1ab","cd_pos":2,"tgt_codon":"cct","src_base":"T","src_aa":"L","tgt_aa":"P","tgt_base":"C","site":"14408"}],"id":"H63-H200","source":"H63","target":"H200"},{"source":"H63","target":"H176","id":"H63-H176","change":[{"site":"10323","tgt_base":"G","tgt_aa":"R","src_aa":"K","cd_pos":2,"label":"orf1ab","tgt_codon":"agg","src_codon":"aag","src_base":"A","pos":10058}]},{"target":"H64","source":"H32","id":"H32-H64","change":[{"src_codon":"cat","cd_pos":3,"label":"orf1ab","tgt_codon":"cac","src_base":"T","pos":249,"site":"514","src_aa":"H","tgt_aa":"H","tgt_base":"C"}]},{"target":"H57","source":"H32","change":[{"site":"29144","tgt_base":"T","tgt_aa":"L","src_aa":"L","cd_pos":1,"label":"N","tgt_codon":"tta","src_codon":"cta","src_base":"C","pos":871}],"id":"H32-H57"},{"id":"H32-H50","change":[{"tgt_base":"T","tgt_aa":"F","src_aa":"L","site":"11083","pos":10818,"src_base":"G","cd_pos":3,"label":"orf1ab","tgt_codon":"ttt","src_codon":"ttg"}],"source":"H32","target":"H50"},{"source":"H32","target":"H100","id":"H32-H100","change":[{"src_base":"C","label":"orf1ab","tgt_codon":"gtt","cd_pos":2,"src_codon":"gct","pos":10844,"site":"11109","tgt_base":"T","src_aa":"A","tgt_aa":"V"}]},{"source":"H32","target":"H97","id":"H32-H97","change":[{"pos":794,"label":"orf1ab","cd_pos":2,"tgt_codon":"atc","src_codon":"acc","src_base":"C","tgt_base":"T","src_aa":"T","tgt_aa":"I","site":"1059"}]},{"change":[{"label":"orf1ab","tgt_codon":"ttc","cd_pos":3,"src_codon":"ttt","src_base":"T","pos":2772,"site":"3037","tgt_base":"C","src_aa":"F","tgt_aa":"F"},{"tgt_base":"A","src_aa":"G","tgt_aa":"D","site":"23403","pos":1841,"src_base":"G","cd_pos":2,"label":"S","tgt_codon":"gat","src_codon":"ggt"}],"id":"H97-H172","source":"H97","target":"H172"},{"target":"H79","source":"H32","change":[{"site":"3145","tgt_base":"T","tgt_aa":"F","src_aa":"L","src_base":"G","tgt_codon":"ttt","label":"orf1ab","cd_pos":3,"src_codon":"ttg","pos":2880}],"id":"H32-H79"},{"id":"H32-I231","change":[{"tgt_base":"T","src_aa":"Q","tgt_aa":"H","site":"25563","pos":"171","label":"ORF3a","cd_pos":3,"tgt_codon":"cat","src_codon":"cag","src_base":"G"}],"source":"H32","target":"I231"},{"source":"I231","target":"H51","change":[{"src_codon":"cta","tgt_codon":"tta","label":"orf1ab","cd_pos":1,"src_base":"C","pos":"18612","site":"18877","tgt_aa":"L","src_aa":"L","tgt_base":"T"}],"id":"I231-H51"},{"target":"H155","source":"H51","id":"H51-H155","change":[{"tgt_aa":"I","src_aa":"I","tgt_base":"T","site":"2113","pos":1848,"src_codon":"atc","label":"orf1ab","cd_pos":3,"tgt_codon":"att","src_base":"C"}]},{"source":"I231","target":"H47","id":"I231-H47","change":[{"pos":"794","cd_pos":2,"tgt_codon":"atc","label":"orf1ab","src_codon":"acc","src_base":"C","tgt_base":"T","src_aa":"T","tgt_aa":"I","site":"1059"}]},{"source":"H47","target":"H205","id":"H47-H205","change":[{"tgt_base":"C","src_aa":null,"tgt_aa":null,"site":"150","pos":150,"tgt_codon":null,"label":"5-UTR","cd_pos":null,"src_codon":null,"src_base":"T"},{"site":"153","tgt_aa":null,"src_aa":null,"tgt_base":"G","src_base":"T","src_codon":null,"label":"5-UTR","tgt_codon":null,"cd_pos":null,"pos":153}]},{"source":"H47","target":"H139","id":"H47-H139","change":[{"site":"11083","tgt_base":"T","tgt_aa":"F","src_aa":"L","src_base":"G","label":"orf1ab","tgt_codon":"ttt","cd_pos":3,"src_codon":"ttg","pos":10818}]},{"source":"H47","target":"H208","change":[{"pos":26,"src_codon":null,"label":"3-UTR","tgt_codon":null,"cd_pos":null,"src_base":"A","src_aa":null,"tgt_aa":null,"tgt_base":"G","site":"29700"}],"id":"H47-H208"},{"target":"H174","source":"H47","id":"H47-H174","change":[{"pos":296,"src_codon":"gct","tgt_codon":"gtt","cd_pos":2,"label":"ORF3a","src_base":"C","src_aa":"A","tgt_aa":"V","tgt_base":"T","site":"25688"}]},{"id":"H174-H187","change":[{"site":"13006","tgt_aa":"A","src_aa":"A","tgt_base":"C","src_base":"T","src_codon":"gct","cd_pos":3,"label":"orf1ab","tgt_codon":"gcc","pos":12741}],"target":"H187","source":"H174"},{"source":"H187","target":"H192","id":"H187-H192","change":[{"pos":2367,"tgt_codon":"tat","label":"S","cd_pos":3,"src_codon":"tac","src_base":"C","tgt_base":"T","src_aa":"Y","tgt_aa":"Y","site":"23929"}]},{"id":"H47-H179","change":[{"pos":186,"src_base":"C","src_codon":null,"tgt_codon":null,"label":"5-UTR","cd_pos":null,"tgt_aa":null,"src_aa":null,"tgt_base":"T","site":"186"}],"source":"H47","target":"H179"},{"source":"H47","target":"H89","change":[{"site":"10582","tgt_base":"T","src_aa":"D","tgt_aa":"D","tgt_codon":"gat","label":"orf1ab","cd_pos":3,"src_codon":"gac","src_base":"C","pos":10317}],"id":"H47-H89"},{"source":"H47","target":"H112","change":[{"src_aa":"T","tgt_aa":"I","tgt_base":"T","site":"18656","pos":18391,"src_base":"C","src_codon":"acc","tgt_codon":"atc","cd_pos":2,"label":"orf1ab"}],"id":"H47-H112"},{"change":[{"src_codon":"cct","cd_pos":1,"label":"orf1ab","tgt_codon":"tct","src_base":"C","pos":18663,"site":"18928","tgt_aa":"S","src_aa":"P","tgt_base":"T"}],"id":"H47-H138","target":"H138","source":"H47"},{"source":"H47","target":"H102","change":[{"pos":5990,"tgt_codon":"gta","cd_pos":2,"label":"orf1ab","src_codon":"gca","src_base":"C","tgt_base":"T","src_aa":"A","tgt_aa":"V","site":"6255"}],"id":"H47-H102"},{"change":[{"src_base":"G","tgt_codon":null,"label":"igs:N|ORF10","cd_pos":null,"src_codon":null,"pos":20,"site":"29553","tgt_base":"A","tgt_aa":null,"src_aa":null}],"id":"H47-H84","source":"H47","target":"H84"},{"change":[{"site":"17639","tgt_base":"T","src_aa":"S","tgt_aa":"L","label":"orf1ab","cd_pos":2,"tgt_codon":"tta","src_codon":"tca","src_base":"C","pos":17374}],"id":"H47-H201","source":"H47","target":"H201"},{"target":"H169","source":"H47","id":"H47-H169","change":[{"tgt_base":"T","tgt_aa":"L","src_aa":"S","site":"27964","pos":71,"label":"ORF8","tgt_codon":"tta","cd_pos":2,"src_codon":"tca","src_base":"C"}]},{"change":[{"pos":568,"src_base":"T","src_codon":"ttc","cd_pos":1,"label":"orf1ab","tgt_codon":"ctc","src_aa":"F","tgt_aa":"L","tgt_base":"C","site":"833"}],"id":"H169-H150","source":"H169","target":"H150"},{"change":[{"pos":2827,"src_codon":"agt","label":"S","tgt_codon":"cgt","cd_pos":1,"src_base":"A","src_aa":"S","tgt_aa":"R","tgt_base":"C","site":"24389"},{"pos":2828,"src_base":"G","cd_pos":2,"label":"S","tgt_codon":"act","src_codon":"agt","tgt_base":"C","tgt_aa":"T","src_aa":"S","site":"24390"}],"id":"H47-H96","source":"H47","target":"H96"},{"target":"H86","source":"I231","change":[{"tgt_codon":"tat","label":"orf1ab","cd_pos":3,"src_codon":"tac","src_base":"C","pos":"2151","site":"2416","tgt_base":"T","src_aa":"Y","tgt_aa":"Y"}],"id":"I231-H86"},{"target":"H198","source":"H86","id":"H86-H198","change":[{"label":"orf1ab","tgt_codon":"cat","cd_pos":3,"src_codon":"cag","src_base":"G","pos":8106,"site":"8371","tgt_base":"T","tgt_aa":"H","src_aa":"Q"}]},{"change":[],"id":"I231-H87","source":"I231","target":"H87"},{"target":"I201","source":"H87","change":[],"id":"H87-I201"},{"change":null,"id":"I201-I200","source":"I201","target":"I200"},{"source":"I200","target":"H189","id":"I200-H189","change":null},{"target":"H90","source":"I200","change":null,"id":"I200-H90"},{"source":"I201","target":"H186","change":[{"tgt_aa":"N","src_aa":"N","tgt_base":"T","site":"15324","pos":"15059","src_base":"C","src_codon":"aac","label":"orf1ab","cd_pos":3,"tgt_codon":"aat"},{"pos":"13","src_codon":"ctt","cd_pos":1,"label":"S","tgt_codon":"ttt","src_base":"C","src_aa":"L","tgt_aa":"F","tgt_base":"T","site":"21575"},{"pos":"171","src_codon":"cat","label":"ORF3a","cd_pos":3,"tgt_codon":"cag","src_base":"T","tgt_aa":"Q","src_aa":"H","tgt_base":"G","site":"25563"}],"id":"I201-H186"},{"id":"H32-H52","change":[{"pos":2013,"src_base":"C","label":"S","cd_pos":3,"tgt_codon":"tgt","src_codon":"tgc","tgt_base":"T","src_aa":"C","tgt_aa":"C","site":"23575"}],"source":"H32","target":"H52"},{"id":"H32-H135","change":[{"tgt_base":"C","tgt_aa":"L","src_aa":"L","site":"28688","pos":415,"src_base":"T","cd_pos":1,"label":"N","tgt_codon":"ctg","src_codon":"ttg"}],"target":"H135","source":"H32"},{"source":"H32","target":"H31","change":[{"src_base":"G","src_codon":"agg","label":"N","cd_pos":2,"tgt_codon":"aag","pos":608,"site":"28881","src_aa":"R","tgt_aa":"K","tgt_base":"A"},{"site":"28882","src_aa":"R","tgt_aa":"R","tgt_base":"A","src_base":"G","src_codon":"agg","cd_pos":3,"label":"N","tgt_codon":"aga","pos":609},{"label":"N","tgt_codon":"cga","cd_pos":1,"src_codon":"gga","src_base":"G","pos":610,"site":"28883","tgt_base":"C","src_aa":"G","tgt_aa":"R"}],"id":"H32-H31"},{"source":"H31","target":"H49","change":[{"site":"27046","tgt_base":"T","tgt_aa":"M","src_aa":"T","src_base":"C","label":"M","cd_pos":2,"tgt_codon":"atg","src_codon":"acg","pos":524}],"id":"H31-H49"},{"target":"H133","source":"H49","id":"H49-H133","change":[{"site":"13402","tgt_aa":"*","src_aa":"Y","tgt_base":"G","src_codon":"tat","label":"orf1ab","cd_pos":3,"tgt_codon":"tag","src_base":"T","pos":13137}]},{"change":[{"tgt_base":"C","tgt_aa":"T","src_aa":"M","site":"27046","pos":524,"tgt_codon":"acg","cd_pos":2,"label":"M","src_codon":"atg","src_base":"T"}],"id":"H133-H95","source":"H133","target":"H95"},{"source":"H49","target":"H195","change":[{"tgt_base":"G","tgt_aa":"C","src_aa":"Y","site":"25958","pos":566,"src_base":"A","label":"ORF3a","tgt_codon":"tgt","cd_pos":2,"src_codon":"tat"}],"id":"H49-H195"},{"id":"H195-H181","change":[{"src_base":"C","tgt_codon":"gtt","label":"S","cd_pos":2,"src_codon":"gct","pos":2492,"site":"24054","tgt_base":"T","tgt_aa":"V","src_aa":"A"}],"target":"H181","source":"H195"},{"id":"H49-H114","change":[{"src_base":"G","cd_pos":3,"label":"orf1ab","tgt_codon":"ttt","src_codon":"ttg","pos":10818,"site":"11083","tgt_base":"T","src_aa":"L","tgt_aa":"F"}],"source":"H49","target":"H114"},{"id":"H114-H119","change":[{"site":"27046","src_aa":"M","tgt_aa":"T","tgt_base":"C","src_base":"T","src_codon":"atg","label":"M","tgt_codon":"acg","cd_pos":2,"pos":524}],"source":"H114","target":"H119"},{"target":"H101","source":"H49","id":"H49-H101","change":[{"site":"6255","tgt_aa":"V","src_aa":"A","tgt_base":"T","src_codon":"gca","label":"orf1ab","cd_pos":2,"tgt_codon":"gta","src_base":"C","pos":5990}]},{"id":"H49-H161","change":[{"pos":19766,"src_base":"C","src_codon":"gcc","cd_pos":3,"label":"orf1ab","tgt_codon":"gca","src_aa":"A","tgt_aa":"A","tgt_base":"A","site":"20031"}],"target":"H161","source":"H49"},{"change":[{"pos":2827,"src_base":"A","src_codon":"agt","label":"S","tgt_codon":"cgt","cd_pos":1,"tgt_aa":"R","src_aa":"S","tgt_base":"C","site":"24389"},{"site":"24390","tgt_base":"C","tgt_aa":"T","src_aa":"S","src_base":"G","tgt_codon":"act","label":"S","cd_pos":2,"src_codon":"agt","pos":2828}],"id":"H49-H134","target":"H134","source":"H49"},{"id":"H134-H94","change":[{"src_base":"T","src_codon":"atg","cd_pos":2,"label":"M","tgt_codon":"acg","pos":524,"site":"27046","src_aa":"M","tgt_aa":"T","tgt_base":"C"}],"target":"H94","source":"H134"},{"source":"H134","target":"H132","change":[{"src_base":"T","label":"orf1ab","cd_pos":3,"tgt_codon":"tag","src_codon":"tat","pos":13137,"site":"13402","tgt_base":"G","src_aa":"Y","tgt_aa":"*"}],"id":"H134-H132"},{"id":"H49-H65","change":[{"cd_pos":2,"label":"N","tgt_codon":"aat","src_codon":"act","src_base":"C","pos":71,"site":"28344","tgt_base":"A","tgt_aa":"N","src_aa":"T"}],"source":"H49","target":"H65"},{"id":"H49-H76","change":[{"tgt_base":"A","src_aa":"Q","tgt_aa":"K","site":"22277","pos":715,"cd_pos":1,"label":"S","tgt_codon":"aaa","src_codon":"caa","src_base":"C"}],"target":"H76","source":"H49"},{"source":"H49","target":"I239","change":[{"pos":"1524","cd_pos":3,"label":"S","tgt_codon":"tat","src_codon":"tac","src_base":"C","tgt_base":"T","src_aa":"Y","tgt_aa":"Y","site":"23086"}],"id":"H49-I239"},{"source":"I239","target":"H190","id":"I239-H190","change":[]},{"id":"I239-H194","change":[{"pos":"822","src_codon":"ttc","tgt_codon":"ttt","label":"N","cd_pos":3,"src_base":"C","tgt_aa":"F","src_aa":"F","tgt_base":"T","site":"29095"}],"source":"I239","target":"H194"},{"source":"H49","target":"H74","change":[{"src_aa":"L","tgt_aa":"F","tgt_base":"T","site":"3145","pos":2880,"src_codon":"ttg","label":"orf1ab","cd_pos":3,"tgt_codon":"ttt","src_base":"G"}],"id":"H49-H74"},{"source":"H31","target":"H39","change":[{"site":"313","tgt_base":"T","tgt_aa":"L","src_aa":"L","tgt_codon":"ctt","label":"orf1ab","cd_pos":3,"src_codon":"ctc","src_base":"C","pos":48}],"id":"H31-H39"},{"change":[{"pos":19253,"src_base":"G","cd_pos":3,"tgt_codon":"ttt","label":"orf1ab","src_codon":"ttg","tgt_base":"T","tgt_aa":"F","src_aa":"L","site":"19518"}],"id":"H39-H156","target":"H156","source":"H39"},{"source":"H31","target":"H40","change":[{"src_codon":"aat","cd_pos":3,"label":"orf1ab","tgt_codon":"aac","src_base":"T","pos":19574,"site":"19839","tgt_aa":"N","src_aa":"N","tgt_base":"C"}],"id":"H31-H40"},{"source":"H40","target":"H75","id":"H40-H75","change":[{"pos":2880,"tgt_codon":"ttt","label":"orf1ab","cd_pos":3,"src_codon":"ttg","src_base":"G","tgt_base":"T","tgt_aa":"F","src_aa":"L","site":"3145"}]},{"change":[{"site":"29700","tgt_base":"G","src_aa":null,"tgt_aa":null,"cd_pos":null,"label":"3-UTR","tgt_codon":null,"src_codon":null,"src_base":"A","pos":26}],"id":"H31-H160","target":"H160","source":"H31"},{"id":"H31-H38","change":[{"tgt_aa":"E","src_aa":"D","tgt_base":"A","site":"3373","pos":3108,"src_base":"C","src_codon":"gac","cd_pos":3,"label":"orf1ab","tgt_codon":"gaa"}],"target":"H38","source":"H31"},{"target":"H209","source":"H31","id":"H31-H209","change":[{"tgt_codon":"tat","label":"orf1ab","cd_pos":3,"src_codon":"tac","src_base":"C","pos":16622,"site":"16887","tgt_base":"T","src_aa":"Y","tgt_aa":"Y"}]},{"source":"H31","target":"H203","change":[{"site":"25791","src_aa":"C","tgt_aa":"C","tgt_base":"T","src_base":"C","src_codon":"tgc","label":"ORF3a","tgt_codon":"tgt","cd_pos":3,"pos":399}],"id":"H31-H203"},{"target":"H46","source":"H32","change":[{"src_base":"A","src_codon":null,"label":"5-UTR","cd_pos":null,"tgt_codon":null,"pos":187,"site":"187","src_aa":null,"tgt_aa":null,"tgt_base":"G"}],"id":"H32-H46"},{"target":"H71","source":"H32","change":[{"pos":3788,"src_base":"C","label":"S","tgt_codon":"cta","cd_pos":2,"src_codon":"cca","tgt_base":"T","src_aa":"P","tgt_aa":"L","site":"25350"}],"id":"H32-H71"},{"change":[{"tgt_base":"T","src_aa":"N","tgt_aa":"N","site":"15324","pos":15059,"src_base":"C","tgt_codon":"aat","label":"orf1ab","cd_pos":3,"src_codon":"aac"}],"id":"H32-H88","source":"H32","target":"H88"},{"id":"H88-H175","change":[{"tgt_codon":"ttt","label":"orf1ab","cd_pos":3,"src_codon":"ttg","src_base":"G","pos":10818,"site":"11083","tgt_base":"T","tgt_aa":"F","src_aa":"L"},{"site":"16887","src_aa":"Y","tgt_aa":"Y","tgt_base":"T","src_base":"C","src_codon":"tac","label":"orf1ab","tgt_codon":"tat","cd_pos":3,"pos":16622}],"source":"H88","target":"H175"},{"id":"H88-H207","change":[{"label":"orf1ab","cd_pos":2,"tgt_codon":"atc","src_codon":"acc","src_base":"C","pos":18391,"site":"18656","tgt_base":"T","src_aa":"T","tgt_aa":"I"}],"target":"H207","source":"H88"},{"id":"H32-H62","change":[{"src_base":"A","src_codon":"gat","label":"M","tgt_codon":"ggt","cd_pos":2,"pos":8,"site":"26530","tgt_aa":"G","src_aa":"D","tgt_base":"G"}],"source":"H32","target":"H62"},{"change":[{"site":"884","tgt_aa":"C","src_aa":"R","tgt_base":"T","src_codon":"cgt","cd_pos":1,"tgt_codon":"tgt","label":"orf1ab","src_base":"C","pos":619}],"id":"H62-H197","source":"H62","target":"H197"},{"source":"I272","target":"H66","change":[],"id":"I272-H66"},{"target":"H106","source":"H18","change":[{"pos":82,"src_base":"C","src_codon":"cta","label":"E","tgt_codon":"tta","cd_pos":1,"tgt_aa":"L","src_aa":"L","tgt_base":"T","site":"26326"}],"id":"H18-H106"},{"source":"H106","target":"H105","id":"H106-H105","change":[{"site":"18060","tgt_base":"T","tgt_aa":"L","src_aa":"L","src_base":"C","label":"orf1ab","cd_pos":3,"tgt_codon":"ctt","src_codon":"ctc","pos":17795}]},{"id":"H18-H19","change":[{"src_aa":"T","tgt_aa":"I","tgt_base":"T","site":"9438","pos":9173,"src_codon":"aca","label":"orf1ab","cd_pos":2,"tgt_codon":"ata","src_base":"C"}],"source":"H18","target":"H19"},{"change":[{"tgt_codon":"ata","label":"orf1ab","cd_pos":1,"src_codon":"gta","src_base":"G","pos":1132,"site":"1397","tgt_base":"A","tgt_aa":"I","src_aa":"V"},{"pos":415,"src_base":"T","cd_pos":1,"tgt_codon":"ctg","label":"N","src_codon":"ttg","tgt_base":"C","tgt_aa":"L","src_aa":"L","site":"28688"}],"id":"H18-H21","source":"H18","target":"H21"},{"id":"H21-H171","change":[{"tgt_base":"T","src_aa":"L","tgt_aa":"L","site":"2455","pos":2190,"src_base":"C","label":"orf1ab","cd_pos":3,"tgt_codon":"ctt","src_codon":"ctc"},{"tgt_base":"G","src_aa":"F","tgt_aa":"L","site":"11083","pos":10818,"src_base":"T","label":"orf1ab","cd_pos":3,"tgt_codon":"ttg","src_codon":"ttt"}],"target":"H171","source":"H21"},{"target":"H126","source":"H21","id":"H21-H126","change":[{"src_codon":"ttg","tgt_codon":"ttt","label":"orf1ab","cd_pos":3,"src_base":"G","pos":19253,"site":"19518","src_aa":"L","tgt_aa":"F","tgt_base":"T"}]},{"source":"H21","target":"I145","change":[],"id":"H21-I145"},{"id":"I145-H116","change":[{"src_codon":"acc","tgt_codon":"atc","cd_pos":2,"label":"orf1ab","src_base":"C","pos":"794","site":"1059","src_aa":"T","tgt_aa":"I","tgt_base":"T"},{"src_base":"A","label":"orf1ab","cd_pos":1,"tgt_codon":"gta","src_codon":"ata","pos":"1132","site":"1397","tgt_base":"G","src_aa":"I","tgt_aa":"V"},{"tgt_base":"T","src_aa":"L","tgt_aa":"L","site":"28688","pos":"415","label":"N","cd_pos":1,"tgt_codon":"ttg","src_codon":"ctg","src_base":"C"}],"source":"I145","target":"H116"},{"change":null,"id":"I145-I144","source":"I145","target":"I144"},{"target":"H53","source":"I144","id":"I144-H53","change":null},{"change":null,"id":"I144-H170","target":"H170","source":"I144"},{"change":[{"src_base":"G","src_codon":"ttg","label":"orf1ab","cd_pos":3,"tgt_codon":"ttt","pos":2880,"site":"3145","src_aa":"L","tgt_aa":"F","tgt_base":"T"}],"id":"H21-H78","source":"H21","target":"H78"},{"source":"H21","target":"H70","change":[{"site":"9479","src_aa":"G","tgt_aa":"C","tgt_base":"T","src_codon":"ggt","label":"orf1ab","tgt_codon":"tgt","cd_pos":1,"src_base":"G","pos":9214}],"id":"H21-H70"},{"change":[{"tgt_base":"G","tgt_aa":"R","src_aa":"K","site":"10323","pos":10058,"label":"orf1ab","cd_pos":2,"tgt_codon":"agg","src_codon":"aag","src_base":"A"}],"id":"H21-H121","target":"H121","source":"H21"},{"source":"H21","target":"H43","change":[{"site":"29374","tgt_base":"A","tgt_aa":"E","src_aa":"E","src_base":"G","label":"N","cd_pos":3,"tgt_codon":"gaa","src_codon":"gag","pos":1101}],"id":"H21-H43"},{"change":[{"src_base":"C","cd_pos":1,"tgt_codon":"tgt","label":"orf1ab","src_codon":"cgt","pos":"619","site":"884","tgt_base":"T","tgt_aa":"C","src_aa":"R"}],"id":"H21-I149","target":"I149","source":"H21"},{"id":"I149-H173","change":[{"tgt_base":"T","src_aa":null,"tgt_aa":null,"site":"241","pos":"241","tgt_codon":null,"label":"5-UTR","cd_pos":null,"src_codon":null,"src_base":"C"},{"pos":"415","src_codon":"ctg","label":"N","cd_pos":1,"tgt_codon":"ttg","src_base":"C","tgt_aa":"L","src_aa":"L","tgt_base":"T","site":"28688"}],"source":"I149","target":"H173"},{"change":[{"pos":"8388","cd_pos":3,"label":"orf1ab","tgt_codon":"att","src_codon":"atg","src_base":"G","tgt_base":"T","tgt_aa":"I","src_aa":"M","site":"8653"}],"id":"I149-H42","target":"H42","source":"I149"},{"id":"H21-H115","change":[{"src_aa":"T","tgt_aa":"I","tgt_base":"T","site":"1059","pos":794,"src_base":"C","src_codon":"acc","cd_pos":2,"label":"orf1ab","tgt_codon":"atc"},{"tgt_base":"T","tgt_aa":"I","src_aa":"T","site":"23934","pos":2372,"src_base":"C","cd_pos":2,"label":"S","tgt_codon":"ata","src_codon":"aca"},{"src_base":"T","label":"N","cd_pos":3,"tgt_codon":"gcc","src_codon":"gct","pos":375,"site":"28648","tgt_base":"C","tgt_aa":"A","src_aa":"A"}],"target":"H115","source":"H21"},{"target":"H80","source":"H1","change":[{"src_base":"G","src_codon":"ttg","label":"orf1ab","tgt_codon":"ttt","cd_pos":3,"pos":2880,"site":"3145","src_aa":"L","tgt_aa":"F","tgt_base":"T"}],"id":"H1-H80"},{"source":"H1","target":"H73","id":"H1-H73","change":[{"tgt_base":"C","tgt_aa":"H","src_aa":"H","site":"514","pos":249,"src_base":"T","label":"orf1ab","cd_pos":3,"tgt_codon":"cac","src_codon":"cat"},{"tgt_codon":"gta","label":"orf1ab","cd_pos":2,"src_codon":"gca","src_base":"C","pos":5990,"site":"6255","tgt_base":"T","src_aa":"A","tgt_aa":"V"}]},{"change":[{"site":"27147","tgt_base":"C","tgt_aa":"H","src_aa":"D","tgt_codon":"cac","label":"M","cd_pos":1,"src_codon":"gac","src_base":"G","pos":625}],"id":"H1-H17","target":"H17","source":"H1"},{"source":"H1","target":"H3","id":"H1-H3","change":[{"tgt_base":"T","tgt_aa":"Y","src_aa":"H","site":"21707","pos":145,"src_base":"C","tgt_codon":"tat","label":"S","cd_pos":1,"src_codon":"cat"}]},{"target":"H9","source":"H1","change":[{"pos":581,"src_codon":"tca","label":"N","cd_pos":2,"tgt_codon":"tta","src_base":"C","tgt_aa":"L","src_aa":"S","tgt_base":"T","site":"28854"}],"id":"H1-H9"},{"source":"H1","target":"H5","change":[{"src_base":"G","tgt_codon":"gtt","cd_pos":2,"label":"ORF3a","src_codon":"ggt","pos":752,"site":"26144","tgt_base":"T","src_aa":"G","tgt_aa":"V"}],"id":"H1-H5"},{"change":[{"src_codon":"tat","label":"orf1ab","tgt_codon":"tac","cd_pos":3,"src_base":"T","pos":13664,"site":"13929","tgt_aa":"Y","src_aa":"Y","tgt_base":"C"}],"id":"H5-H27","source":"H5","target":"H27"},{"source":"H27","target":"H69","id":"H27-H69","change":[{"src_base":"C","src_codon":"tac","label":"orf1ab","cd_pos":3,"tgt_codon":"tat","pos":11439,"site":"11704","tgt_aa":"Y","src_aa":"Y","tgt_base":"T"}]},{"change":[{"site":"22661","tgt_aa":"F","src_aa":"V","tgt_base":"T","src_base":"G","src_codon":"gtc","tgt_codon":"ttc","cd_pos":1,"label":"S","pos":1099}],"id":"H5-H12","target":"H12","source":"H5"},{"source":"H1","target":"H124","change":[{"src_codon":"cta","tgt_codon":"tta","label":"E","cd_pos":1,"src_base":"C","pos":82,"site":"26326","tgt_aa":"L","src_aa":"L","tgt_base":"T"}],"id":"H1-H124"},{"id":"H124-H56","change":[{"site":"11410","tgt_base":"A","src_aa":"L","tgt_aa":"L","cd_pos":3,"label":"orf1ab","tgt_codon":"tta","src_codon":"ttg","src_base":"G","pos":11145}],"target":"H56","source":"H124"},{"source":"H1","target":"H123","id":"H1-H123","change":[{"tgt_aa":"I","src_aa":"S","tgt_base":"T","site":"28851","pos":578,"src_codon":"agt","tgt_codon":"att","label":"N","cd_pos":2,"src_base":"G"}]},{"change":[{"pos":16622,"src_codon":"tac","tgt_codon":"tat","cd_pos":3,"label":"orf1ab","src_base":"C","src_aa":"Y","tgt_aa":"Y","tgt_base":"T","site":"16887"}],"id":"H1-H125","source":"H1","target":"H125"},{"change":[{"site":"186","src_aa":null,"tgt_aa":null,"tgt_base":"T","src_base":"C","src_codon":null,"cd_pos":null,"label":"5-UTR","tgt_codon":null,"pos":186}],"id":"H1-H25","target":"H25","source":"H1"},{"target":"H29","source":"H1","id":"H1-H29","change":[{"pos":9659,"src_base":"C","label":"orf1ab","cd_pos":2,"tgt_codon":"gta","src_codon":"gca","tgt_base":"T","tgt_aa":"V","src_aa":"A","site":"9924"}]},{"change":[{"pos":78,"label":"ORF10","tgt_codon":"tat","cd_pos":3,"src_codon":"tac","src_base":"C","tgt_base":"T","tgt_aa":"Y","src_aa":"Y","site":"29635"}],"id":"H1-H55","target":"H55","source":"H1"},{"target":"H33","source":"H55","id":"H55-H33","change":[{"pos":10818,"src_base":"G","src_codon":"ttg","label":"orf1ab","cd_pos":3,"tgt_codon":"ttt","tgt_aa":"F","src_aa":"L","tgt_base":"T","site":"11083"}]},{"source":"H33","target":"H142","id":"H33-H142","change":[{"tgt_base":"T","tgt_aa":"I","src_aa":"T","site":"18656","pos":18391,"src_base":"C","cd_pos":2,"label":"orf1ab","tgt_codon":"atc","src_codon":"acc"}]},{"change":[{"pos":8958,"src_base":"C","label":"orf1ab","cd_pos":3,"tgt_codon":"cat","src_codon":"cac","tgt_base":"T","tgt_aa":"H","src_aa":"H","site":"9223"}],"id":"H142-H147","target":"H147","source":"H142"},{"change":[{"site":"21575","tgt_aa":"F","src_aa":"L","tgt_base":"T","src_base":"C","src_codon":"ctt","cd_pos":1,"label":"S","tgt_codon":"ttt","pos":13}],"id":"H33-H145","target":"H145","source":"H33"},{"target":"H23","source":"H1","id":"H1-H23","change":[{"src_aa":"N","tgt_aa":"N","tgt_base":"T","site":"24034","pos":2472,"src_codon":"aac","cd_pos":3,"label":"S","tgt_codon":"aat","src_base":"C"}]},{"change":[{"src_base":"C","src_codon":"tca","tgt_codon":"tta","cd_pos":2,"label":"N","pos":581,"site":"28854","tgt_aa":"L","src_aa":"S","tgt_base":"T"}],"id":"H23-H22","source":"H23","target":"H22"},{"target":"H10","source":"H1","change":[{"pos":17108,"src_base":"C","tgt_codon":"gct","label":"orf1ab","cd_pos":3,"src_codon":"gcc","tgt_base":"T","src_aa":"A","tgt_aa":"A","site":"17373"}],"id":"H1-H10"},{"target":"H15","source":"H13","change":[{"tgt_base":"C","src_aa":"L","tgt_aa":"L","site":"4402","pos":4137,"cd_pos":3,"label":"orf1ab","tgt_codon":"ctc","src_codon":"ctt","src_base":"T"},{"site":"5062","tgt_base":"T","tgt_aa":"F","src_aa":"L","label":"orf1ab","cd_pos":3,"tgt_codon":"ttt","src_codon":"ttg","src_base":"G","pos":4797}],"id":"H13-H15"},{"source":"H15","target":"H37","change":[{"pos":8517,"src_base":"T","src_codon":"agt","cd_pos":3,"tgt_codon":"agc","label":"orf1ab","src_aa":"S","tgt_aa":"S","tgt_base":"C","site":"8782"},{"tgt_base":"T","tgt_aa":"V","src_aa":"G","site":"26144","pos":752,"src_base":"G","label":"ORF3a","cd_pos":2,"tgt_codon":"gtt","src_codon":"ggt"}],"id":"H15-H37"},{"target":"H60","source":"H13","id":"H13-H60","change":[{"pos":16622,"cd_pos":3,"label":"orf1ab","tgt_codon":"tat","src_codon":"tac","src_base":"C","tgt_base":"T","tgt_aa":"Y","src_aa":"Y","site":"16887"}]},{"id":"H13-H35","change":[{"site":"23403","tgt_base":"G","tgt_aa":"G","src_aa":"D","tgt_codon":"ggt","cd_pos":2,"label":"S","src_codon":"gat","src_base":"A","pos":1841}],"source":"H13","target":"H35"},{"id":"H13-H4","change":[{"pos":17795,"src_base":"C","src_codon":"ctc","label":"orf1ab","cd_pos":3,"tgt_codon":"ctt","src_aa":"L","tgt_aa":"L","tgt_base":"T","site":"18060"}],"target":"H4","source":"H13"},{"id":"H4-I65","change":[{"site":"17858","tgt_base":"G","tgt_aa":"C","src_aa":"Y","src_base":"A","label":"orf1ab","cd_pos":2,"tgt_codon":"tgt","src_codon":"tat","pos":"17593"}],"target":"I65","source":"H4"},{"id":"I65-H128","change":[],"target":"H128","source":"I65"},{"change":[{"pos":"17482","src_base":"C","src_codon":"cct","cd_pos":2,"label":"orf1ab","tgt_codon":"ctt","src_aa":"P","tgt_aa":"L","tgt_base":"T","site":"17747"}],"id":"I65-H44","target":"H44","source":"I65"},{"source":"H44","target":"H108","id":"H44-H108","change":[{"pos":150,"src_codon":null,"label":"5-UTR","cd_pos":null,"tgt_codon":null,"src_base":"T","src_aa":null,"tgt_aa":null,"tgt_base":"C","site":"150"},{"site":"153","tgt_base":"G","tgt_aa":null,"src_aa":null,"src_base":"T","cd_pos":null,"label":"5-UTR","tgt_codon":null,"src_codon":null,"pos":153}]},{"source":"H44","target":"H58","id":"H44-H58","change":[{"tgt_codon":"gct","label":"S","cd_pos":2,"src_codon":"gtt","src_base":"T","pos":1448,"site":"23010","tgt_base":"C","tgt_aa":"A","src_aa":"V"}]},{"target":"H168","source":"H44","id":"H44-H168","change":[{"site":"6310","tgt_aa":"S","src_aa":"S","tgt_base":"T","src_base":"C","src_codon":"agc","cd_pos":3,"label":"orf1ab","tgt_codon":"agt","pos":6045}]},{"change":[{"label":"ORF6","cd_pos":3,"tgt_codon":"aat","src_codon":"aag","src_base":"G","pos":126,"site":"27327","tgt_base":"T","tgt_aa":"N","src_aa":"K"}],"id":"H168-H109","target":"H109","source":"H168"},{"id":"H44-H159","change":[{"pos":14540,"tgt_codon":"tat","label":"orf1ab","cd_pos":3,"src_codon":"tac","src_base":"C","tgt_base":"T","tgt_aa":"Y","src_aa":"Y","site":"14805"}],"source":"H44","target":"H159"},{"target":"H34","source":"H44","change":[{"src_aa":"T","tgt_aa":"I","tgt_base":"T","site":"5784","pos":5519,"src_codon":"act","cd_pos":2,"label":"orf1ab","tgt_codon":"att","src_base":"C"}],"id":"H44-H34"},{"id":"H44-H152","change":[{"tgt_aa":"L","src_aa":"L","tgt_base":"T","site":"18877","pos":18612,"src_codon":"cta","label":"orf1ab","tgt_codon":"tta","cd_pos":1,"src_base":"C"}],"target":"H152","source":"H44"},{"change":[{"tgt_aa":"K","src_aa":"R","tgt_base":"A","site":"28881","pos":608,"src_base":"G","src_codon":"agg","tgt_codon":"aag","label":"N","cd_pos":2}],"id":"H44-H164","target":"H164","source":"H44"},{"change":[{"site":"24694","tgt_base":"T","src_aa":"G","tgt_aa":"G","tgt_codon":"ggt","label":"S","cd_pos":3,"src_codon":"gga","src_base":"A","pos":"3132"}],"id":"H44-I44","target":"I44","source":"H44"},{"change":[],"id":"I44-H127","source":"I44","target":"H127"},{"source":"I44","target":"H185","change":[{"pos":"9180","label":"orf1ab","cd_pos":3,"tgt_codon":"ctc","src_codon":"ctt","src_base":"T","tgt_base":"C","tgt_aa":"L","src_aa":"L","site":"9445"}],"id":"I44-H185"},{"id":"H185-H196","change":[{"cd_pos":3,"label":"orf1ab","tgt_codon":"ctc","src_codon":"ctt","src_base":"T","pos":17795,"site":"18060","tgt_base":"C","tgt_aa":"L","src_aa":"L"}],"target":"H196","source":"H185"},{"id":"H185-H182","change":[{"src_aa":"I","tgt_aa":"T","tgt_base":"C","site":"17531","pos":17266,"src_base":"T","src_codon":"ata","label":"orf1ab","cd_pos":2,"tgt_codon":"aca"},{"pos":18491,"src_base":"G","src_codon":"ccg","tgt_codon":"cct","label":"orf1ab","cd_pos":3,"tgt_aa":"P","src_aa":"P","tgt_base":"T","site":"18756"}],"target":"H182","source":"H185"},{"id":"H44-H158","change":[{"tgt_aa":"F","src_aa":"L","tgt_base":"T","site":"11083","pos":10818,"src_base":"G","src_codon":"ttg","tgt_codon":"ttt","cd_pos":3,"label":"orf1ab"}],"target":"H158","source":"H44"},{"change":[{"site":"27384","tgt_base":"C","src_aa":"D","tgt_aa":"D","src_base":"T","cd_pos":3,"label":"ORF6","tgt_codon":"gac","src_codon":"gat","pos":183}],"id":"H158-H166","target":"H166","source":"H158"},{"id":"H166-H110","change":[{"site":"11083","tgt_base":"G","src_aa":"F","tgt_aa":"L","cd_pos":3,"label":"orf1ab","tgt_codon":"ttg","src_codon":"ttt","src_base":"T","pos":10818}],"source":"H166","target":"H110"},{"source":"H158","target":"H167","id":"H158-H167","change":[{"src_aa":"Y","tgt_aa":"Y","tgt_base":"T","site":"16887","pos":16622,"src_codon":"tac","cd_pos":3,"label":"orf1ab","tgt_codon":"tat","src_base":"C"}]},{"change":[{"src_codon":"tac","tgt_codon":"tat","label":"orf1ab","cd_pos":3,"src_base":"C","pos":11439,"site":"11704","src_aa":"Y","tgt_aa":"Y","tgt_base":"T"}],"id":"H44-H151","target":"H151","source":"H44"},{"target":"H61","source":"H44","change":[{"src_base":"A","label":"orf1ab","cd_pos":3,"tgt_codon":"ccg","src_codon":"cca","pos":16202,"site":"16467","tgt_base":"G","tgt_aa":"P","src_aa":"P"},{"pos":1623,"src_base":"C","label":"S","cd_pos":3,"tgt_codon":"ttt","src_codon":"ttc","tgt_base":"T","tgt_aa":"F","src_aa":"F","site":"23185"}],"id":"H44-H61"},{"source":"H44","target":"H153","id":"H44-H153","change":[{"site":"29700","tgt_base":"G","tgt_aa":null,"src_aa":null,"src_base":"A","cd_pos":null,"label":"3-UTR","tgt_codon":null,"src_codon":null,"pos":26}]},{"source":"H44","target":"H130","id":"H44-H130","change":[{"site":"22988","tgt_aa":"S","src_aa":"G","tgt_base":"A","src_codon":"ggt","tgt_codon":"agt","cd_pos":1,"label":"S","src_base":"G","pos":1426}]},{"source":"H130","target":"H165","change":[{"src_codon":"ctt","label":"S","cd_pos":1,"tgt_codon":"ttt","src_base":"C","pos":13,"site":"21575","tgt_aa":"F","src_aa":"L","tgt_base":"T"}],"id":"H130-H165"},{"id":"H44-I57","change":[{"pos":"62","src_base":"G","label":"3-UTR","tgt_codon":null,"cd_pos":null,"src_codon":null,"tgt_base":"T","tgt_aa":null,"src_aa":null,"site":"29736"}],"source":"H44","target":"I57"},{"change":[],"id":"I57-H149","source":"I57","target":"H149"},{"id":"I57-H107","change":[{"src_base":"T","label":"orf1ab","cd_pos":2,"tgt_codon":"cct","src_codon":"ctt","pos":"17482","site":"17747","tgt_base":"C","src_aa":"L","tgt_aa":"P"}],"source":"I57","target":"H107"},{"source":"H44","target":"H131","id":"H44-H131","change":[{"src_base":"T","label":"orf1ab","cd_pos":3,"tgt_codon":"ctg","src_codon":"ctt","pos":15662,"site":"15927","tgt_base":"G","tgt_aa":"L","src_aa":"L"},{"src_base":"C","label":"M","cd_pos":3,"tgt_codon":"ctt","src_codon":"ctc","pos":414,"site":"26936","tgt_base":"T","tgt_aa":"L","src_aa":"L"}]},{"change":[{"tgt_aa":"N","src_aa":"N","tgt_base":"T","site":"832","pos":567,"src_codon":"aac","label":"orf1ab","tgt_codon":"aat","cd_pos":3,"src_base":"C"}],"id":"H44-H83","target":"H83","source":"H44"},{"id":"H44-H85","change":[{"pos":8,"src_base":"A","tgt_codon":"ggt","label":"M","cd_pos":2,"src_codon":"gat","tgt_base":"G","src_aa":"D","tgt_aa":"G","site":"26530"}],"source":"H44","target":"H85"},{"source":"H20","target":"H30","id":"H20-H30","change":[{"pos":5990,"label":"orf1ab","cd_pos":2,"tgt_codon":"gta","src_codon":"gca","src_base":"C","tgt_base":"T","src_aa":"A","tgt_aa":"V","site":"6255"}]},{"id":"H2-H11","change":[{"pos":8517,"src_base":"T","label":"orf1ab","cd_pos":3,"tgt_codon":"agc","src_codon":"agt","tgt_base":"C","src_aa":"S","tgt_aa":"S","site":"8782"}],"source":"H2","target":"H11"}]]